{
  "CSVInfo": {
    "filename": "US_MAP_DATA",
    "update": "Apr 15 2021 12:28PM",
    "disclaimer": "Case and Death data updated as of Apr 15 2021 12:28PM.  Testing data updated as of Apr 15 2021  6:57PM",
    "fieldpropertymap": [
      {
        "abbr": "abbr"
      },
      {
        "fips": "fips"
      },
      {
        "name": "jurisdiction"
      },
      {
        "tot_cases": "Total Cases"
      },
      {
        "tot_death": "Total Death"
      },
      {
        "death_100k": "Death_100k"
      },
      {
        "new_cases07": "CasesInLast7Days"
      },
      {
        "new_deaths07": "DeathsInLast7Days"
      },
      {
        "Seven_day_avg_new_cases_per_100k": "Seven_day_avg_new_cases_per_100k"
      },
      {
        "Seven_day_avg_new_deaths_per_100k": "Seven_day_avg_new_deaths_per_100k"
      },
      {
        "Seven_day_cum_new_cases_per_100k": "Seven_day_cum_new_cases_per_100k"
      },
      {
        "Seven_day_cum_new_deaths_per_100k": "Seven_day_cum_new_deaths_per_100k"
      },
      {
        "incidence": "RatePer100000"
      }
    ]
  },
  "US_MAP_DATA": [
    {
      "abbr": "AK",
      "tot_cases": 62876,
      "tot_cases_last_24_hours": 0,
      "conf_cases": 0,
      "prob_cases": 0,
      "new_cases07": 1181,
      "new_deaths07": 1,
      "Seven_day_avg_new_cases_per_100k": 23.1,
      "Seven_day_avg_new_deaths_per_100k": 0,
      "Seven_day_cum_new_cases_per_100k": 161.4,
      "Seven_day_cum_new_deaths_per_100k": 0.1,
      "tot_death": 310,
      "tot_death_last_24_hours": 0,
      "conf_death": null,
      "prob_death": null,
      "death_100k": 42,
      "incidence": 8595,
      "id": 2,
      "fips": "02",
      "name": "Alaska"
    },
    {
      "abbr": "AL",
      "tot_cases": 520780,
      "tot_cases_last_24_hours": 0,
      "conf_cases": 404401,
      "prob_cases": 116379,
      "new_cases07": 2178,
      "new_deaths07": 76,
      "Seven_day_avg_new_cases_per_100k": 6.4,
      "Seven_day_avg_new_deaths_per_100k": 0.2,
      "Seven_day_cum_new_cases_per_100k": 44.4,
      "Seven_day_cum_new_deaths_per_100k": 1.6,
      "tot_death": 10728,
      "tot_death_last_24_hours": 0,
      "conf_death": 8446,
      "prob_death": 2282,
      "death_100k": 218,
      "incidence": 10621,
      "id": 1,
      "fips": "01",
      "name": "Alabama"
    },
    {
      "abbr": "AR",
      "tot_cases": 332666,
      "tot_cases_last_24_hours": 0,
      "conf_cases": 0,
      "prob_cases": 0,
      "new_cases07": 1161,
      "new_deaths07": 21,
      "Seven_day_avg_new_cases_per_100k": 5.5,
      "Seven_day_avg_new_deaths_per_100k": 0.1,
      "Seven_day_cum_new_cases_per_100k": 38.5,
      "Seven_day_cum_new_deaths_per_100k": 0.7,
      "tot_death": 5680,
      "tot_death_last_24_hours": 0,
      "conf_death": null,
      "prob_death": null,
      "death_100k": 188,
      "incidence": 11023,
      "id": 5,
      "fips": "05",
      "name": "Arkansas"
    },
    {
      "abbr": "AS",
      "tot_cases": 0,
      "tot_cases_last_24_hours": 0,
      "conf_cases": 0,
      "prob_cases": 0,
      "new_cases07": 0,
      "new_deaths07": 0,
      "Seven_day_avg_new_cases_per_100k": 0,
      "Seven_day_avg_new_deaths_per_100k": 0,
      "Seven_day_cum_new_cases_per_100k": 0,
      "Seven_day_cum_new_deaths_per_100k": 0,
      "tot_death": 0,
      "tot_death_last_24_hours": 0,
      "conf_death": null,
      "prob_death": null,
      "death_100k": null,
      "incidence": 0,
      "id": 60,
      "fips": "60",
      "name": "American Samoa"
    },
    {
      "abbr": "AZ",
      "tot_cases": 851265,
      "tot_cases_last_24_hours": 0,
      "conf_cases": 790076,
      "prob_cases": 61189,
      "new_cases07": 4410,
      "new_deaths07": 92,
      "Seven_day_avg_new_cases_per_100k": 8.7,
      "Seven_day_avg_new_deaths_per_100k": 0.2,
      "Seven_day_cum_new_cases_per_100k": 60.6,
      "Seven_day_cum_new_deaths_per_100k": 1.3,
      "tot_death": 17109,
      "tot_death_last_24_hours": 0,
      "conf_death": 15182,
      "prob_death": 1927,
      "death_100k": 235,
      "incidence": 11695,
      "id": 4,
      "fips": "04",
      "name": "Arizona"
    },
    {
      "abbr": "CA",
      "tot_cases": 3606882,
      "tot_cases_last_24_hours": 0,
      "conf_cases": 0,
      "prob_cases": 0,
      "new_cases07": 20823,
      "new_deaths07": 713,
      "Seven_day_avg_new_cases_per_100k": 7.5,
      "Seven_day_avg_new_deaths_per_100k": 0.3,
      "Seven_day_cum_new_cases_per_100k": 52.7,
      "Seven_day_cum_new_deaths_per_100k": 1.8,
      "tot_death": 59372,
      "tot_death_last_24_hours": 0,
      "conf_death": null,
      "prob_death": null,
      "death_100k": 150,
      "incidence": 9128,
      "id": 6,
      "fips": "06",
      "name": "California"
    },
    {
      "abbr": "CO",
      "tot_cases": 483818,
      "tot_cases_last_24_hours": 0,
      "conf_cases": 453257,
      "prob_cases": 30561,
      "new_cases07": 11651,
      "new_deaths07": 33,
      "Seven_day_avg_new_cases_per_100k": 28.9,
      "Seven_day_avg_new_deaths_per_100k": 0.1,
      "Seven_day_cum_new_cases_per_100k": 202.3,
      "Seven_day_cum_new_deaths_per_100k": 0.6,
      "tot_death": 6172,
      "tot_death_last_24_hours": 0,
      "conf_death": 5438,
      "prob_death": 734,
      "death_100k": 107,
      "incidence": 8402,
      "id": 8,
      "fips": "08",
      "name": "Colorado"
    },
    {
      "abbr": "CT",
      "tot_cases": 327298,
      "tot_cases_last_24_hours": 0,
      "conf_cases": 301324,
      "prob_cases": 25974,
      "new_cases07": 8531,
      "new_deaths07": 49,
      "Seven_day_avg_new_cases_per_100k": 34.2,
      "Seven_day_avg_new_deaths_per_100k": 0.2,
      "Seven_day_cum_new_cases_per_100k": 239.3,
      "Seven_day_cum_new_deaths_per_100k": 1.4,
      "tot_death": 7984,
      "tot_death_last_24_hours": 0,
      "conf_death": 6568,
      "prob_death": 1416,
      "death_100k": 223,
      "incidence": 9180,
      "id": 9,
      "fips": "09",
      "name": "Connecticut"
    },
    {
      "abbr": "DC",
      "tot_cases": 46209,
      "tot_cases_last_24_hours": 0,
      "conf_cases": 0,
      "prob_cases": 0,
      "new_cases07": 881,
      "new_deaths07": 12,
      "Seven_day_avg_new_cases_per_100k": 17.8,
      "Seven_day_avg_new_deaths_per_100k": 0.2,
      "Seven_day_cum_new_cases_per_100k": 124.8,
      "Seven_day_cum_new_deaths_per_100k": 1.7,
      "tot_death": 1088,
      "tot_death_last_24_hours": 0,
      "conf_death": null,
      "prob_death": null,
      "death_100k": 154,
      "incidence": 6548,
      "id": 11,
      "fips": "11",
      "name": "District of Columbia"
    },
    {
      "abbr": "DE",
      "tot_cases": 99515,
      "tot_cases_last_24_hours": 0,
      "conf_cases": 93154,
      "prob_cases": 6361,
      "new_cases07": 2473,
      "new_deaths07": 24,
      "Seven_day_avg_new_cases_per_100k": 36.3,
      "Seven_day_avg_new_deaths_per_100k": 0.4,
      "Seven_day_cum_new_cases_per_100k": 254,
      "Seven_day_cum_new_deaths_per_100k": 2.5,
      "tot_death": 1591,
      "tot_death_last_24_hours": 0,
      "conf_death": 1451,
      "prob_death": 140,
      "death_100k": 163,
      "incidence": 10220,
      "id": 10,
      "fips": "10",
      "name": "Delaware"
    },
    {
      "abbr": "FL",
      "tot_cases": 2101365,
      "tot_cases_last_24_hours": 0,
      "conf_cases": 0,
      "prob_cases": 0,
      "new_cases07": 44006,
      "new_deaths07": 342,
      "Seven_day_avg_new_cases_per_100k": 29.3,
      "Seven_day_avg_new_deaths_per_100k": 0.2,
      "Seven_day_cum_new_cases_per_100k": 204.9,
      "Seven_day_cum_new_deaths_per_100k": 1.6,
      "tot_death": 34164,
      "tot_death_last_24_hours": 0,
      "conf_death": null,
      "prob_death": null,
      "death_100k": 159,
      "incidence": 9784,
      "id": 12,
      "fips": "12",
      "name": "Florida"
    },
    {
      "abbr": "FSM",
      "tot_cases": 1,
      "tot_cases_last_24_hours": 0,
      "conf_cases": 1,
      "prob_cases": 0,
      "new_cases07": 0,
      "new_deaths07": 0,
      "Seven_day_avg_new_cases_per_100k": 0,
      "Seven_day_avg_new_deaths_per_100k": 0,
      "Seven_day_cum_new_cases_per_100k": 0,
      "Seven_day_cum_new_deaths_per_100k": 0,
      "tot_death": 0,
      "tot_death_last_24_hours": 0,
      "conf_death": null,
      "prob_death": null,
      "death_100k": null,
      "incidence": 1,
      "id": 64,
      "fips": "64",
      "name": "Federated States of Micronesia"
    },
    {
      "abbr": "GA",
      "tot_cases": 1078379,
      "tot_cases_last_24_hours": 0,
      "conf_cases": 864895,
      "prob_cases": 213484,
      "new_cases07": 10180,
      "new_deaths07": 295,
      "Seven_day_avg_new_cases_per_100k": 13.7,
      "Seven_day_avg_new_deaths_per_100k": 0.4,
      "Seven_day_cum_new_cases_per_100k": 95.9,
      "Seven_day_cum_new_deaths_per_100k": 2.8,
      "tot_death": 19600,
      "tot_death_last_24_hours": 0,
      "conf_death": 17072,
      "prob_death": 2528,
      "death_100k": 184,
      "incidence": 10157,
      "id": 13,
      "fips": "13",
      "name": "Georgia"
    },
    {
      "abbr": "GU",
      "tot_cases": 7856,
      "tot_cases_last_24_hours": 0,
      "conf_cases": 0,
      "prob_cases": 0,
      "new_cases07": 28,
      "new_deaths07": 0,
      "Seven_day_avg_new_cases_per_100k": 2.4,
      "Seven_day_avg_new_deaths_per_100k": 0,
      "Seven_day_cum_new_cases_per_100k": 16.9,
      "Seven_day_cum_new_deaths_per_100k": 0,
      "tot_death": 136,
      "tot_death_last_24_hours": 0,
      "conf_death": null,
      "prob_death": null,
      "death_100k": 82,
      "incidence": 4739,
      "id": 66,
      "fips": "66",
      "name": "Guam"
    },
    {
      "abbr": "HI",
      "tot_cases": 29984,
      "tot_cases_last_24_hours": 0,
      "conf_cases": 0,
      "prob_cases": 0,
      "new_cases07": 600,
      "new_deaths07": 6,
      "Seven_day_avg_new_cases_per_100k": 6.1,
      "Seven_day_avg_new_deaths_per_100k": 0.1,
      "Seven_day_cum_new_cases_per_100k": 42.4,
      "Seven_day_cum_new_deaths_per_100k": 0.4,
      "tot_death": 470,
      "tot_death_last_24_hours": 0,
      "conf_death": null,
      "prob_death": null,
      "death_100k": 33,
      "incidence": 2118,
      "id": 15,
      "fips": "15",
      "name": "Hawaii"
    },
    {
      "abbr": "IA",
      "tot_cases": 358395,
      "tot_cases_last_24_hours": 0,
      "conf_cases": 0,
      "prob_cases": 0,
      "new_cases07": 3573,
      "new_deaths07": 21,
      "Seven_day_avg_new_cases_per_100k": 16.2,
      "Seven_day_avg_new_deaths_per_100k": 0.1,
      "Seven_day_cum_new_cases_per_100k": 113.3,
      "Seven_day_cum_new_deaths_per_100k": 0.7,
      "tot_death": 5857,
      "tot_death_last_24_hours": 0,
      "conf_death": null,
      "prob_death": null,
      "death_100k": 185,
      "incidence": 11359,
      "id": 19,
      "fips": "19",
      "name": "Iowa"
    },
    {
      "abbr": "ID",
      "tot_cases": 184347,
      "tot_cases_last_24_hours": 0,
      "conf_cases": 147950,
      "prob_cases": 36397,
      "new_cases07": 1816,
      "new_deaths07": 26,
      "Seven_day_avg_new_cases_per_100k": 14.5,
      "Seven_day_avg_new_deaths_per_100k": 0.2,
      "Seven_day_cum_new_cases_per_100k": 101.6,
      "Seven_day_cum_new_deaths_per_100k": 1.5,
      "tot_death": 2006,
      "tot_death_last_24_hours": 0,
      "conf_death": 1747,
      "prob_death": 259,
      "death_100k": 112,
      "incidence": 10316,
      "id": 16,
      "fips": "16",
      "name": "Idaho"
    },
    {
      "abbr": "IL",
      "tot_cases": 1288934,
      "tot_cases_last_24_hours": 0,
      "conf_cases": 1288934,
      "prob_cases": 0,
      "new_cases07": 23477,
      "new_deaths07": 163,
      "Seven_day_avg_new_cases_per_100k": 26.5,
      "Seven_day_avg_new_deaths_per_100k": 0.2,
      "Seven_day_cum_new_cases_per_100k": 185.3,
      "Seven_day_cum_new_deaths_per_100k": 1.3,
      "tot_death": 23865,
      "tot_death_last_24_hours": 0,
      "conf_death": 21570,
      "prob_death": 2295,
      "death_100k": 188,
      "incidence": 10172,
      "id": 17,
      "fips": "17",
      "name": "Illinois"
    },
    {
      "abbr": "IN",
      "tot_cases": 701971,
      "tot_cases_last_24_hours": 0,
      "conf_cases": 0,
      "prob_cases": 0,
      "new_cases07": 8261,
      "new_deaths07": 88,
      "Seven_day_avg_new_cases_per_100k": 17.5,
      "Seven_day_avg_new_deaths_per_100k": 0.2,
      "Seven_day_cum_new_cases_per_100k": 122.7,
      "Seven_day_cum_new_deaths_per_100k": 1.3,
      "tot_death": 13187,
      "tot_death_last_24_hours": 0,
      "conf_death": 12782,
      "prob_death": 405,
      "death_100k": 195,
      "incidence": 10427,
      "id": 18,
      "fips": "18",
      "name": "Indiana"
    },
    {
      "abbr": "KS",
      "tot_cases": 305320,
      "tot_cases_last_24_hours": 0,
      "conf_cases": 246931,
      "prob_cases": 58389,
      "new_cases07": 1553,
      "new_deaths07": 20,
      "Seven_day_avg_new_cases_per_100k": 7.6,
      "Seven_day_avg_new_deaths_per_100k": 0.1,
      "Seven_day_cum_new_cases_per_100k": 53.3,
      "Seven_day_cum_new_deaths_per_100k": 0.7,
      "tot_death": 4944,
      "tot_death_last_24_hours": 0,
      "conf_death": null,
      "prob_death": null,
      "death_100k": 169,
      "incidence": 10480,
      "id": 20,
      "fips": "20",
      "name": "Kansas"
    },
    {
      "abbr": "KY",
      "tot_cases": 434922,
      "tot_cases_last_24_hours": 0,
      "conf_cases": 329906,
      "prob_cases": 105016,
      "new_cases07": 4062,
      "new_deaths07": 62,
      "Seven_day_avg_new_cases_per_100k": 13,
      "Seven_day_avg_new_deaths_per_100k": 0.2,
      "Seven_day_cum_new_cases_per_100k": 90.9,
      "Seven_day_cum_new_deaths_per_100k": 1.4,
      "tot_death": 6285,
      "tot_death_last_24_hours": 0,
      "conf_death": 5688,
      "prob_death": 597,
      "death_100k": 140,
      "incidence": 9735,
      "id": 21,
      "fips": "21",
      "name": "Kentucky"
    },
    {
      "abbr": "LA",
      "tot_cases": 450673,
      "tot_cases_last_24_hours": 0,
      "conf_cases": 0,
      "prob_cases": 0,
      "new_cases07": 3018,
      "new_deaths07": 79,
      "Seven_day_avg_new_cases_per_100k": 9.3,
      "Seven_day_avg_new_deaths_per_100k": 0.2,
      "Seven_day_cum_new_cases_per_100k": 64.9,
      "Seven_day_cum_new_deaths_per_100k": 1.7,
      "tot_death": 10264,
      "tot_death_last_24_hours": 0,
      "conf_death": 9385,
      "prob_death": 879,
      "death_100k": 220,
      "incidence": 9694,
      "id": 22,
      "fips": "22",
      "name": "Louisiana"
    },
    {
      "abbr": "MA",
      "tot_cases": 634562,
      "tot_cases_last_24_hours": 0,
      "conf_cases": 624666,
      "prob_cases": 9896,
      "new_cases07": 12841,
      "new_deaths07": 68,
      "Seven_day_avg_new_cases_per_100k": 26.6,
      "Seven_day_avg_new_deaths_per_100k": 0.1,
      "Seven_day_cum_new_cases_per_100k": 186.3,
      "Seven_day_cum_new_deaths_per_100k": 1,
      "tot_death": 17290,
      "tot_death_last_24_hours": 0,
      "conf_death": 17082,
      "prob_death": 208,
      "death_100k": 250,
      "incidence": 9207,
      "id": 25,
      "fips": "25",
      "name": "Massachusetts"
    },
    {
      "abbr": "MD",
      "tot_cases": 431795,
      "tot_cases_last_24_hours": 0,
      "conf_cases": 0,
      "prob_cases": 0,
      "new_cases07": 9972,
      "new_deaths07": 102,
      "Seven_day_avg_new_cases_per_100k": 23.6,
      "Seven_day_avg_new_deaths_per_100k": 0.2,
      "Seven_day_cum_new_cases_per_100k": 164.9,
      "Seven_day_cum_new_deaths_per_100k": 1.7,
      "tot_death": 8512,
      "tot_death_last_24_hours": 0,
      "conf_death": 8326,
      "prob_death": 186,
      "death_100k": 140,
      "incidence": 7142,
      "id": 24,
      "fips": "24",
      "name": "Maryland"
    },
    {
      "abbr": "ME",
      "tot_cases": 55953,
      "tot_cases_last_24_hours": 0,
      "conf_cases": 42185,
      "prob_cases": 13768,
      "new_cases07": 2954,
      "new_deaths07": 10,
      "Seven_day_avg_new_cases_per_100k": 31.4,
      "Seven_day_avg_new_deaths_per_100k": 0.1,
      "Seven_day_cum_new_cases_per_100k": 219.8,
      "Seven_day_cum_new_deaths_per_100k": 0.7,
      "tot_death": 758,
      "tot_death_last_24_hours": 0,
      "conf_death": 734,
      "prob_death": 24,
      "death_100k": 56,
      "incidence": 4162,
      "id": 23,
      "fips": "23",
      "name": "Maine"
    },
    {
      "abbr": "MI",
      "tot_cases": 850583,
      "tot_cases_last_24_hours": 0,
      "conf_cases": 764519,
      "prob_cases": 86064,
      "new_cases07": 55091,
      "new_deaths07": 184,
      "Seven_day_avg_new_cases_per_100k": 78.8,
      "Seven_day_avg_new_deaths_per_100k": 0.3,
      "Seven_day_cum_new_cases_per_100k": 551.6,
      "Seven_day_cum_new_deaths_per_100k": 1.8,
      "tot_death": 17694,
      "tot_death_last_24_hours": 0,
      "conf_death": 16619,
      "prob_death": 1075,
      "death_100k": 177,
      "incidence": 8517,
      "id": 26,
      "fips": "26",
      "name": "Michigan"
    },
    {
      "abbr": "MN",
      "tot_cases": 547101,
      "tot_cases_last_24_hours": 0,
      "conf_cases": 0,
      "prob_cases": 0,
      "new_cases07": 14443,
      "new_deaths07": 70,
      "Seven_day_avg_new_cases_per_100k": 36.6,
      "Seven_day_avg_new_deaths_per_100k": 0.2,
      "Seven_day_cum_new_cases_per_100k": 256.1,
      "Seven_day_cum_new_deaths_per_100k": 1.2,
      "tot_death": 7056,
      "tot_death_last_24_hours": 0,
      "conf_death": 6593,
      "prob_death": 463,
      "death_100k": 125,
      "incidence": 9701,
      "id": 27,
      "fips": "27",
      "name": "Minnesota"
    },
    {
      "abbr": "MO",
      "tot_cases": 586636,
      "tot_cases_last_24_hours": 0,
      "conf_cases": 0,
      "prob_cases": 0,
      "new_cases07": 4746,
      "new_deaths07": 120,
      "Seven_day_avg_new_cases_per_100k": 11.1,
      "Seven_day_avg_new_deaths_per_100k": 0.3,
      "Seven_day_cum_new_cases_per_100k": 77.3,
      "Seven_day_cum_new_deaths_per_100k": 2,
      "tot_death": 8630,
      "tot_death_last_24_hours": 0,
      "conf_death": null,
      "prob_death": null,
      "death_100k": 140,
      "incidence": 9558,
      "id": 29,
      "fips": "29",
      "name": "Missouri"
    },
    {
      "abbr": "MP",
      "tot_cases": 161,
      "tot_cases_last_24_hours": 0,
      "conf_cases": 161,
      "prob_cases": 0,
      "new_cases07": 1,
      "new_deaths07": 0,
      "Seven_day_avg_new_cases_per_100k": 0.3,
      "Seven_day_avg_new_deaths_per_100k": 0,
      "Seven_day_cum_new_cases_per_100k": 0,
      "Seven_day_cum_new_deaths_per_100k": 0,
      "tot_death": 2,
      "tot_death_last_24_hours": 0,
      "conf_death": 2,
      "prob_death": 0,
      "death_100k": 3,
      "incidence": 0,
      "id": 69,
      "fips": "69",
      "name": "Northern Mariana Islands"
    },
    {
      "abbr": "MS",
      "tot_cases": 308521,
      "tot_cases_last_24_hours": 0,
      "conf_cases": 188856,
      "prob_cases": 119665,
      "new_cases07": 1670,
      "new_deaths07": 38,
      "Seven_day_avg_new_cases_per_100k": 8,
      "Seven_day_avg_new_deaths_per_100k": 0.2,
      "Seven_day_cum_new_cases_per_100k": 56.1,
      "Seven_day_cum_new_deaths_per_100k": 1.3,
      "tot_death": 7127,
      "tot_death_last_24_hours": 0,
      "conf_death": 4926,
      "prob_death": 2201,
      "death_100k": 239,
      "incidence": 10366,
      "id": 28,
      "fips": "28",
      "name": "Mississippi"
    },
    {
      "abbr": "MT",
      "tot_cases": 106631,
      "tot_cases_last_24_hours": 0,
      "conf_cases": 98794,
      "prob_cases": 7837,
      "new_cases07": 1033,
      "new_deaths07": 11,
      "Seven_day_avg_new_cases_per_100k": 13.8,
      "Seven_day_avg_new_deaths_per_100k": 0.2,
      "Seven_day_cum_new_cases_per_100k": 96.7,
      "Seven_day_cum_new_deaths_per_100k": 1,
      "tot_death": 1526,
      "tot_death_last_24_hours": 0,
      "conf_death": 1526,
      "prob_death": 0,
      "death_100k": 142,
      "incidence": 9977,
      "id": 30,
      "fips": "30",
      "name": "Montana"
    },
    {
      "abbr": "NC",
      "tot_cases": 938784,
      "tot_cases_last_24_hours": 0,
      "conf_cases": 807504,
      "prob_cases": 131280,
      "new_cases07": 13974,
      "new_deaths07": 113,
      "Seven_day_avg_new_cases_per_100k": 19,
      "Seven_day_avg_new_deaths_per_100k": 0.2,
      "Seven_day_cum_new_cases_per_100k": 133.2,
      "Seven_day_cum_new_deaths_per_100k": 1.1,
      "tot_death": 12325,
      "tot_death_last_24_hours": 0,
      "conf_death": 10880,
      "prob_death": 1445,
      "death_100k": 117,
      "incidence": 8951,
      "id": 37,
      "fips": "37",
      "name": "North Carolina"
    },
    {
      "abbr": "ND",
      "tot_cases": 105380,
      "tot_cases_last_24_hours": 0,
      "conf_cases": 97981,
      "prob_cases": 7399,
      "new_cases07": 1016,
      "new_deaths07": 7,
      "Seven_day_avg_new_cases_per_100k": 19.1,
      "Seven_day_avg_new_deaths_per_100k": 0.1,
      "Seven_day_cum_new_cases_per_100k": 133.3,
      "Seven_day_cum_new_deaths_per_100k": 0.9,
      "tot_death": 1475,
      "tot_death_last_24_hours": 0,
      "conf_death": null,
      "prob_death": null,
      "death_100k": 193,
      "incidence": 13828,
      "id": 38,
      "fips": "38",
      "name": "North Dakota"
    },
    {
      "abbr": "NE",
      "tot_cases": 215074,
      "tot_cases_last_24_hours": 0,
      "conf_cases": 0,
      "prob_cases": 0,
      "new_cases07": 2289,
      "new_deaths07": 43,
      "Seven_day_avg_new_cases_per_100k": 16.9,
      "Seven_day_avg_new_deaths_per_100k": 0.3,
      "Seven_day_cum_new_cases_per_100k": 118.3,
      "Seven_day_cum_new_deaths_per_100k": 2.2,
      "tot_death": 2226,
      "tot_death_last_24_hours": 0,
      "conf_death": null,
      "prob_death": null,
      "death_100k": 115,
      "incidence": 11118,
      "id": 31,
      "fips": "31",
      "name": "Nebraska"
    },
    {
      "abbr": "NH",
      "tot_cases": 89983,
      "tot_cases_last_24_hours": 0,
      "conf_cases": 0,
      "prob_cases": 0,
      "new_cases07": 3048,
      "new_deaths07": 11,
      "Seven_day_avg_new_cases_per_100k": 32,
      "Seven_day_avg_new_deaths_per_100k": 0.1,
      "Seven_day_cum_new_cases_per_100k": 224.2,
      "Seven_day_cum_new_deaths_per_100k": 0.8,
      "tot_death": 1261,
      "tot_death_last_24_hours": 0,
      "conf_death": null,
      "prob_death": null,
      "death_100k": 92,
      "incidence": 6618,
      "id": 33,
      "fips": "33",
      "name": "New Hampshire"
    },
    {
      "abbr": "NJ",
      "tot_cases": 963484,
      "tot_cases_last_24_hours": 0,
      "conf_cases": 845201,
      "prob_cases": 118283,
      "new_cases07": 25505,
      "new_deaths07": 257,
      "Seven_day_avg_new_cases_per_100k": 41,
      "Seven_day_avg_new_deaths_per_100k": 0.4,
      "Seven_day_cum_new_cases_per_100k": 287.2,
      "Seven_day_cum_new_deaths_per_100k": 2.9,
      "tot_death": 25006,
      "tot_death_last_24_hours": 0,
      "conf_death": 22414,
      "prob_death": 2592,
      "death_100k": 281,
      "incidence": 10847,
      "id": 34,
      "fips": "34",
      "name": "New Jersey"
    },
    {
      "abbr": "NM",
      "tot_cases": 194378,
      "tot_cases_last_24_hours": 0,
      "conf_cases": 0,
      "prob_cases": 0,
      "new_cases07": 1389,
      "new_deaths07": 33,
      "Seven_day_avg_new_cases_per_100k": 9.5,
      "Seven_day_avg_new_deaths_per_100k": 0.2,
      "Seven_day_cum_new_cases_per_100k": 66.2,
      "Seven_day_cum_new_deaths_per_100k": 1.6,
      "tot_death": 3996,
      "tot_death_last_24_hours": 0,
      "conf_death": null,
      "prob_death": null,
      "death_100k": 190,
      "incidence": 9270,
      "id": 35,
      "fips": "35",
      "name": "New Mexico"
    },
    {
      "abbr": "NV",
      "tot_cases": 309150,
      "tot_cases_last_24_hours": 0,
      "conf_cases": 0,
      "prob_cases": 0,
      "new_cases07": 3221,
      "new_deaths07": 45,
      "Seven_day_avg_new_cases_per_100k": 14.9,
      "Seven_day_avg_new_deaths_per_100k": 0.2,
      "Seven_day_cum_new_cases_per_100k": 104.6,
      "Seven_day_cum_new_deaths_per_100k": 1.5,
      "tot_death": 5353,
      "tot_death_last_24_hours": 0,
      "conf_death": null,
      "prob_death": null,
      "death_100k": 173,
      "incidence": 10037,
      "id": 32,
      "fips": "32",
      "name": "Nevada"
    },
    {
      "abbr": "NY",
      "tot_cases": 1078165,
      "tot_cases_last_24_hours": 0,
      "conf_cases": 0,
      "prob_cases": 0,
      "new_cases07": 25467,
      "new_deaths07": 154,
      "Seven_day_avg_new_cases_per_100k": 32.9,
      "Seven_day_avg_new_deaths_per_100k": 0.2,
      "Seven_day_cum_new_cases_per_100k": 230.4,
      "Seven_day_cum_new_deaths_per_100k": 1.4,
      "tot_death": 19098,
      "tot_death_last_24_hours": 0,
      "conf_death": null,
      "prob_death": null,
      "death_100k": 172,
      "incidence": 9753,
      "id": 36,
      "fips": "36",
      "name": "New York"
    },
    {
      "abbr": "NYC",
      "tot_cases": 897272,
      "tot_cases_last_24_hours": 0,
      "conf_cases": 741817,
      "prob_cases": 155455,
      "new_cases07": 21026,
      "new_deaths07": 348,
      "Seven_day_avg_new_cases_per_100k": 35.8,
      "Seven_day_avg_new_deaths_per_100k": 0.6,
      "Seven_day_cum_new_cases_per_100k": 250.4,
      "Seven_day_cum_new_deaths_per_100k": 4.1,
      "tot_death": 31993,
      "tot_death_last_24_hours": 0,
      "conf_death": 26920,
      "prob_death": 5073,
      "death_100k": 380,
      "incidence": 10683,
      "id": 57,
      "fips": "57",
      "name": "New York City"
    },
    {
      "abbr": "OH",
      "tot_cases": 1045945,
      "tot_cases_last_24_hours": 0,
      "conf_cases": 882363,
      "prob_cases": 163582,
      "new_cases07": 15081,
      "new_deaths07": 173,
      "Seven_day_avg_new_cases_per_100k": 18.4,
      "Seven_day_avg_new_deaths_per_100k": 0.2,
      "Seven_day_cum_new_cases_per_100k": 129,
      "Seven_day_cum_new_deaths_per_100k": 1.5,
      "tot_death": 18917,
      "tot_death_last_24_hours": 0,
      "conf_death": 18917,
      "prob_death": 0,
      "death_100k": 161,
      "incidence": 8948,
      "id": 39,
      "fips": "39",
      "name": "Ohio"
    },
    {
      "abbr": "OK",
      "tot_cases": 444590,
      "tot_cases_last_24_hours": 0,
      "conf_cases": 350896,
      "prob_cases": 93694,
      "new_cases07": 2201,
      "new_deaths07": 28,
      "Seven_day_avg_new_cases_per_100k": 8,
      "Seven_day_avg_new_deaths_per_100k": 0.1,
      "Seven_day_cum_new_cases_per_100k": 55.6,
      "Seven_day_cum_new_deaths_per_100k": 0.7,
      "tot_death": 6708,
      "tot_death_last_24_hours": 0,
      "conf_death": 5679,
      "prob_death": 1029,
      "death_100k": 169,
      "incidence": 11236,
      "id": 40,
      "fips": "40",
      "name": "Oklahoma"
    },
    {
      "abbr": "OR",
      "tot_cases": 172206,
      "tot_cases_last_24_hours": 0,
      "conf_cases": 172206,
      "prob_cases": 0,
      "new_cases07": 4078,
      "new_deaths07": 15,
      "Seven_day_avg_new_cases_per_100k": 13.8,
      "Seven_day_avg_new_deaths_per_100k": 0.1,
      "Seven_day_cum_new_cases_per_100k": 96.7,
      "Seven_day_cum_new_deaths_per_100k": 0.4,
      "tot_death": 2449,
      "tot_death_last_24_hours": 0,
      "conf_death": 2449,
      "prob_death": 0,
      "death_100k": 58,
      "incidence": 4083,
      "id": 41,
      "fips": "41",
      "name": "Oregon"
    },
    {
      "abbr": "PA",
      "tot_cases": 1087792,
      "tot_cases_last_24_hours": 0,
      "conf_cases": 920147,
      "prob_cases": 167645,
      "new_cases07": 33494,
      "new_deaths07": 237,
      "Seven_day_avg_new_cases_per_100k": 37.4,
      "Seven_day_avg_new_deaths_per_100k": 0.3,
      "Seven_day_cum_new_cases_per_100k": 261.6,
      "Seven_day_cum_new_deaths_per_100k": 1.9,
      "tot_death": 25522,
      "tot_death_last_24_hours": 0,
      "conf_death": null,
      "prob_death": null,
      "death_100k": 199,
      "incidence": 8497,
      "id": 42,
      "fips": "42",
      "name": "Pennsylvania"
    },
    {
      "abbr": "PR",
      "tot_cases": 117836,
      "tot_cases_last_24_hours": 0,
      "conf_cases": 105020,
      "prob_cases": 12816,
      "new_cases07": 7157,
      "new_deaths07": 41,
      "Seven_day_avg_new_cases_per_100k": 32,
      "Seven_day_avg_new_deaths_per_100k": 0.2,
      "Seven_day_cum_new_cases_per_100k": 224.1,
      "Seven_day_cum_new_deaths_per_100k": 1.3,
      "tot_death": 2182,
      "tot_death_last_24_hours": 0,
      "conf_death": 1860,
      "prob_death": 322,
      "death_100k": 68,
      "incidence": 3690,
      "id": 72,
      "fips": "72",
      "name": "Puerto Rico"
    },
    {
      "abbr": "PW",
      "tot_cases": 0,
      "tot_cases_last_24_hours": 0,
      "conf_cases": 0,
      "prob_cases": 0,
      "new_cases07": 0,
      "new_deaths07": 0,
      "Seven_day_avg_new_cases_per_100k": 0,
      "Seven_day_avg_new_deaths_per_100k": 0,
      "Seven_day_cum_new_cases_per_100k": 0,
      "Seven_day_cum_new_deaths_per_100k": 0,
      "tot_death": 0,
      "tot_death_last_24_hours": 0,
      "conf_death": null,
      "prob_death": null,
      "death_100k": null,
      "incidence": 0,
      "id": 70,
      "fips": "70",
      "name": "Palau"
    },
    {
      "abbr": "RI",
      "tot_cases": 143251,
      "tot_cases_last_24_hours": 0,
      "conf_cases": 0,
      "prob_cases": 0,
      "new_cases07": 3226,
      "new_deaths07": 7,
      "Seven_day_avg_new_cases_per_100k": 43.5,
      "Seven_day_avg_new_deaths_per_100k": 0.1,
      "Seven_day_cum_new_cases_per_100k": 304.5,
      "Seven_day_cum_new_deaths_per_100k": 0.7,
      "tot_death": 2642,
      "tot_death_last_24_hours": 0,
      "conf_death": null,
      "prob_death": null,
      "death_100k": 249,
      "incidence": 13522,
      "id": 44,
      "fips": "44",
      "name": "Rhode Island"
    },
    {
      "abbr": "RMI",
      "tot_cases": 4,
      "tot_cases_last_24_hours": 0,
      "conf_cases": 4,
      "prob_cases": 0,
      "new_cases07": 0,
      "new_deaths07": 0,
      "Seven_day_avg_new_cases_per_100k": 0,
      "Seven_day_avg_new_deaths_per_100k": 0,
      "Seven_day_cum_new_cases_per_100k": 0,
      "Seven_day_cum_new_deaths_per_100k": 0,
      "tot_death": 0,
      "tot_death_last_24_hours": 0,
      "conf_death": null,
      "prob_death": null,
      "death_100k": null,
      "incidence": 7,
      "id": 68,
      "fips": "68",
      "name": "Republic of Marshall Islands"
    },
    {
      "abbr": "SC",
      "tot_cases": 564931,
      "tot_cases_last_24_hours": 0,
      "conf_cases": 472786,
      "prob_cases": 92145,
      "new_cases07": 5250,
      "new_deaths07": 21,
      "Seven_day_avg_new_cases_per_100k": 14.6,
      "Seven_day_avg_new_deaths_per_100k": 0.1,
      "Seven_day_cum_new_cases_per_100k": 102,
      "Seven_day_cum_new_deaths_per_100k": 0.4,
      "tot_death": 9304,
      "tot_death_last_24_hours": 0,
      "conf_death": null,
      "prob_death": null,
      "death_100k": 180,
      "incidence": 10972,
      "id": 45,
      "fips": "45",
      "name": "South Carolina"
    },
    {
      "abbr": "SD",
      "tot_cases": 120379,
      "tot_cases_last_24_hours": 0,
      "conf_cases": 0,
      "prob_cases": 0,
      "new_cases07": 1404,
      "new_deaths07": 10,
      "Seven_day_avg_new_cases_per_100k": 22.7,
      "Seven_day_avg_new_deaths_per_100k": 0.2,
      "Seven_day_cum_new_cases_per_100k": 158.7,
      "Seven_day_cum_new_deaths_per_100k": 1.1,
      "tot_death": 1948,
      "tot_death_last_24_hours": 0,
      "conf_death": 1586,
      "prob_death": 362,
      "death_100k": 220,
      "incidence": 13607,
      "id": 46,
      "fips": "46",
      "name": "South Dakota"
    },
    {
      "abbr": "TN",
      "tot_cases": 827579,
      "tot_cases_last_24_hours": 0,
      "conf_cases": 685081,
      "prob_cases": 142498,
      "new_cases07": 8074,
      "new_deaths07": 56,
      "Seven_day_avg_new_cases_per_100k": 16.9,
      "Seven_day_avg_new_deaths_per_100k": 0.1,
      "Seven_day_cum_new_cases_per_100k": 118.2,
      "Seven_day_cum_new_deaths_per_100k": 0.8,
      "tot_death": 12032,
      "tot_death_last_24_hours": 0,
      "conf_death": 9654,
      "prob_death": 2378,
      "death_100k": 176,
      "incidence": 12118,
      "id": 47,
      "fips": "47",
      "name": "Tennessee"
    },
    {
      "abbr": "TX",
      "tot_cases": 2830228,
      "tot_cases_last_24_hours": 0,
      "conf_cases": 0,
      "prob_cases": 0,
      "new_cases07": 21261,
      "new_deaths07": 420,
      "Seven_day_avg_new_cases_per_100k": 10.5,
      "Seven_day_avg_new_deaths_per_100k": 0.2,
      "Seven_day_cum_new_cases_per_100k": 73.3,
      "Seven_day_cum_new_deaths_per_100k": 1.5,
      "tot_death": 48341,
      "tot_death_last_24_hours": 0,
      "conf_death": null,
      "prob_death": null,
      "death_100k": 166,
      "incidence": 9761,
      "id": 48,
      "fips": "48",
      "name": "Texas"
    },
    {
      "abbr": "UT",
      "tot_cases": 391177,
      "tot_cases_last_24_hours": 0,
      "conf_cases": 391177,
      "prob_cases": 0,
      "new_cases07": 2751,
      "new_deaths07": 22,
      "Seven_day_avg_new_cases_per_100k": 12.3,
      "Seven_day_avg_new_deaths_per_100k": 0.1,
      "Seven_day_cum_new_cases_per_100k": 85.8,
      "Seven_day_cum_new_deaths_per_100k": 0.7,
      "tot_death": 2161,
      "tot_death_last_24_hours": 0,
      "conf_death": 2100,
      "prob_death": 61,
      "death_100k": 67,
      "incidence": 12202,
      "id": 49,
      "fips": "49",
      "name": "Utah"
    },
    {
      "abbr": "VA",
      "tot_cases": 641626,
      "tot_cases_last_24_hours": 0,
      "conf_cases": 499675,
      "prob_cases": 141951,
      "new_cases07": 10543,
      "new_deaths07": 93,
      "Seven_day_avg_new_cases_per_100k": 17.7,
      "Seven_day_avg_new_deaths_per_100k": 0.2,
      "Seven_day_cum_new_cases_per_100k": 123.5,
      "Seven_day_cum_new_deaths_per_100k": 1.1,
      "tot_death": 10529,
      "tot_death_last_24_hours": 0,
      "conf_death": 8836,
      "prob_death": 1693,
      "death_100k": 123,
      "incidence": 7517,
      "id": 51,
      "fips": "51",
      "name": "Virginia"
    },
    {
      "abbr": "VI",
      "tot_cases": 3005,
      "tot_cases_last_24_hours": 0,
      "conf_cases": 0,
      "prob_cases": 0,
      "new_cases07": 51,
      "new_deaths07": 0,
      "Seven_day_avg_new_cases_per_100k": 7,
      "Seven_day_avg_new_deaths_per_100k": 0,
      "Seven_day_cum_new_cases_per_100k": 48.7,
      "Seven_day_cum_new_deaths_per_100k": 0,
      "tot_death": 26,
      "tot_death_last_24_hours": 0,
      "conf_death": null,
      "prob_death": null,
      "death_100k": 24,
      "incidence": 2871,
      "id": 78,
      "fips": "78",
      "name": "Virgin Islands"
    },
    {
      "abbr": "VT",
      "tot_cases": 21488,
      "tot_cases_last_24_hours": 0,
      "conf_cases": 0,
      "prob_cases": 0,
      "new_cases07": 1046,
      "new_deaths07": 7,
      "Seven_day_avg_new_cases_per_100k": 24,
      "Seven_day_avg_new_deaths_per_100k": 0.2,
      "Seven_day_cum_new_cases_per_100k": 167.6,
      "Seven_day_cum_new_deaths_per_100k": 1.1,
      "tot_death": 237,
      "tot_death_last_24_hours": 0,
      "conf_death": null,
      "prob_death": null,
      "death_100k": 37,
      "incidence": 3444,
      "id": 50,
      "fips": "50",
      "name": "Vermont"
    },
    {
      "abbr": "WA",
      "tot_cases": 380339,
      "tot_cases_last_24_hours": 0,
      "conf_cases": 0,
      "prob_cases": 0,
      "new_cases07": 8169,
      "new_deaths07": 51,
      "Seven_day_avg_new_cases_per_100k": 15.3,
      "Seven_day_avg_new_deaths_per_100k": 0.1,
      "Seven_day_cum_new_cases_per_100k": 107.3,
      "Seven_day_cum_new_deaths_per_100k": 0.7,
      "tot_death": 5357,
      "tot_death_last_24_hours": 0,
      "conf_death": null,
      "prob_death": null,
      "death_100k": 70,
      "incidence": 4995,
      "id": 53,
      "fips": "53",
      "name": "Washington"
    },
    {
      "abbr": "WI",
      "tot_cases": 648094,
      "tot_cases_last_24_hours": 0,
      "conf_cases": 587561,
      "prob_cases": 60533,
      "new_cases07": 6452,
      "new_deaths07": 46,
      "Seven_day_avg_new_cases_per_100k": 15.8,
      "Seven_day_avg_new_deaths_per_100k": 0.1,
      "Seven_day_cum_new_cases_per_100k": 110.8,
      "Seven_day_cum_new_deaths_per_100k": 0.8,
      "tot_death": 7402,
      "tot_death_last_24_hours": 0,
      "conf_death": 6695,
      "prob_death": 707,
      "death_100k": 127,
      "incidence": 11131,
      "id": 55,
      "fips": "55",
      "name": "Wisconsin"
    },
    {
      "abbr": "WV",
      "tot_cases": 147203,
      "tot_cases_last_24_hours": 0,
      "conf_cases": 116115,
      "prob_cases": 31088,
      "new_cases07": 2829,
      "new_deaths07": 34,
      "Seven_day_avg_new_cases_per_100k": 22.6,
      "Seven_day_avg_new_deaths_per_100k": 0.3,
      "Seven_day_cum_new_cases_per_100k": 157.9,
      "Seven_day_cum_new_deaths_per_100k": 1.9,
      "tot_death": 2756,
      "tot_death_last_24_hours": 0,
      "conf_death": null,
      "prob_death": null,
      "death_100k": 153,
      "incidence": 8214,
      "id": 54,
      "fips": "54",
      "name": "West Virginia"
    },
    {
      "abbr": "WY",
      "tot_cases": 57127,
      "tot_cases_last_24_hours": 0,
      "conf_cases": 48333,
      "prob_cases": 8794,
      "new_cases07": 427,
      "new_deaths07": 2,
      "Seven_day_avg_new_cases_per_100k": 10.5,
      "Seven_day_avg_new_deaths_per_100k": 0.1,
      "Seven_day_cum_new_cases_per_100k": 73.8,
      "Seven_day_cum_new_deaths_per_100k": 0.4,
      "tot_death": 703,
      "tot_death_last_24_hours": 0,
      "conf_death": 703,
      "prob_death": 0,
      "death_100k": 121,
      "incidence": 9871,
      "id": 56,
      "fips": "56",
      "name": "Wyoming"
    },
    {
      "abbr": "USA",
      "tot_cases": 31231869,
      "tot_cases_last_24_hours": 73622,
      "conf_cases": 14363877,
      "prob_cases": 2218143,
      "new_cases07": 487043,
      "new_deaths07": 5000,
      "Seven_day_avg_new_cases_per_100k": 21,
      "Seven_day_avg_new_deaths_per_100k": 0.2,
      "Seven_day_cum_new_cases_per_100k": 146.7,
      "Seven_day_cum_new_deaths_per_100k": 1.5,
      "tot_death": 561356,
      "tot_death_last_24_hours": 831,
      "conf_death": 279830,
      "prob_death": 33281,
      "death_100k": 169,
      "incidence": 9407,
      "id": 0,
      "fips": "00",
      "name": "United States of America"
    }
  ]
}
