{
  "CSVInfo": {
    "filename": "US_MAP_DATA",
    "update": "Nov 30 2021  2:38PM",
    "disclaimer": "Case and Death data updated as of Nov 30 2021  2:38PM.  Testing data updated as of Nov 30 2021  2:42PM",
    "fieldpropertymap": [
      {
        "abbr": "abbr"
      },
      {
        "fips": "fips"
      },
      {
        "name": "jurisdiction"
      },
      {
        "tot_cases": "Total Cases"
      },
      {
        "tot_death": "Total Death"
      },
      {
        "death_100k": "Death_100k"
      },
      {
        "new_cases07": "CasesInLast7Days"
      },
      {
        "new_deaths07": "DeathsInLast7Days"
      },
      {
        "Seven_day_avg_new_cases_per_100k": "Seven_day_avg_new_cases_per_100k"
      },
      {
        "Seven_day_avg_new_deaths_per_100k": "Seven_day_avg_new_deaths_per_100k"
      },
      {
        "Seven_day_cum_new_cases_per_100k": "Seven_day_cum_new_cases_per_100k"
      },
      {
        "Seven_day_cum_new_deaths_per_100k": "Seven_day_cum_new_deaths_per_100k"
      },
      {
        "incidence": "RatePer100000"
      },
      {
        "state_level_community_transmission": "state_level_community_transmission"
      },
      {
        "us_trend_new_case": "us_trend_new_case"
      },
      {
        "us_trend_new_death": "us_trend_new_death"
      }
    ]
  },
  "US_MAP_DATA": [
    {
      "abbr": "AK",
      "tot_cases": 145398,
      "tot_cases_last_24_hours": 0,
      "conf_cases": 0,
      "prob_cases": 0,
      "new_cases07": 1944,
      "new_deaths07": 16,
      "Seven_day_avg_new_cases_per_100k": 38,
      "Seven_day_avg_new_deaths_per_100k": 0.3,
      "Seven_day_cum_new_cases_per_100k": 265.7,
      "Seven_day_cum_new_deaths_per_100k": 2.2,
      "tot_death": 848,
      "tot_death_last_24_hours": 0,
      "conf_death": null,
      "prob_death": null,
      "death_100k": 115,
      "incidence": 19876,
      "id": 2,
      "fips": "02",
      "name": "Alaska",
      "state_level_community_transmission": "high",
      "us_trend_new_case": 706,
      "us_trend_new_death": 1,
      "us_trend_maxdate": "2021-11-29"
    },
    {
      "abbr": "AL",
      "tot_cases": 845763,
      "tot_cases_last_24_hours": 0,
      "conf_cases": 621520,
      "prob_cases": 224243,
      "new_cases07": 1981,
      "new_deaths07": 33,
      "Seven_day_avg_new_cases_per_100k": 5.8,
      "Seven_day_avg_new_deaths_per_100k": 0.1,
      "Seven_day_cum_new_cases_per_100k": 40.4,
      "Seven_day_cum_new_deaths_per_100k": 0.7,
      "tot_death": 16123,
      "tot_death_last_24_hours": 0,
      "conf_death": 12487,
      "prob_death": 3636,
      "death_100k": 328,
      "incidence": 17249,
      "id": 1,
      "fips": "01",
      "name": "Alabama",
      "state_level_community_transmission": "moderate",
      "us_trend_new_case": 477,
      "us_trend_new_death": 3,
      "us_trend_maxdate": "2021-11-29"
    },
    {
      "abbr": "AR",
      "tot_cases": 527794,
      "tot_cases_last_24_hours": 0,
      "conf_cases": 0,
      "prob_cases": 0,
      "new_cases07": 3354,
      "new_deaths07": 35,
      "Seven_day_avg_new_cases_per_100k": 15.9,
      "Seven_day_avg_new_deaths_per_100k": 0.2,
      "Seven_day_cum_new_cases_per_100k": 111.1,
      "Seven_day_cum_new_deaths_per_100k": 1.2,
      "tot_death": 8655,
      "tot_death_last_24_hours": 0,
      "conf_death": null,
      "prob_death": null,
      "death_100k": 286,
      "incidence": 17489,
      "id": 5,
      "fips": "05",
      "name": "Arkansas",
      "state_level_community_transmission": "high",
      "us_trend_new_case": 207,
      "us_trend_new_death": 2,
      "us_trend_maxdate": "2021-11-29"
    },
    {
      "abbr": "AS",
      "tot_cases": 5,
      "tot_cases_last_24_hours": 0,
      "conf_cases": 0,
      "prob_cases": 0,
      "new_cases07": 0,
      "new_deaths07": 0,
      "Seven_day_avg_new_cases_per_100k": 0,
      "Seven_day_avg_new_deaths_per_100k": 0,
      "Seven_day_cum_new_cases_per_100k": 0,
      "Seven_day_cum_new_deaths_per_100k": 0,
      "tot_death": 0,
      "tot_death_last_24_hours": 0,
      "conf_death": null,
      "prob_death": null,
      "death_100k": null,
      "incidence": 11,
      "id": 60,
      "fips": "60",
      "name": "American Samoa",
      "state_level_community_transmission": "",
      "us_trend_new_case": null,
      "us_trend_new_death": null,
      "us_trend_maxdate": "null"
    },
    {
      "abbr": "AZ",
      "tot_cases": 1266809,
      "tot_cases_last_24_hours": 0,
      "conf_cases": 1145858,
      "prob_cases": 120951,
      "new_cases07": 21682,
      "new_deaths07": 288,
      "Seven_day_avg_new_cases_per_100k": 42.6,
      "Seven_day_avg_new_deaths_per_100k": 0.6,
      "Seven_day_cum_new_cases_per_100k": 297.9,
      "Seven_day_cum_new_deaths_per_100k": 4,
      "tot_death": 22230,
      "tot_death_last_24_hours": 0,
      "conf_death": 19630,
      "prob_death": 2600,
      "death_100k": 305,
      "incidence": 17404,
      "id": 4,
      "fips": "04",
      "name": "Arizona",
      "state_level_community_transmission": "high",
      "us_trend_new_case": 1961,
      "us_trend_new_death": 1,
      "us_trend_maxdate": "2021-11-29"
    },
    {
      "abbr": "CA",
      "tot_cases": 5057974,
      "tot_cases_last_24_hours": 0,
      "conf_cases": 4801843,
      "prob_cases": 256131,
      "new_cases07": 28202,
      "new_deaths07": 457,
      "Seven_day_avg_new_cases_per_100k": 10.2,
      "Seven_day_avg_new_deaths_per_100k": 0.2,
      "Seven_day_cum_new_cases_per_100k": 71.4,
      "Seven_day_cum_new_deaths_per_100k": 1.2,
      "tot_death": 73656,
      "tot_death_last_24_hours": 0,
      "conf_death": null,
      "prob_death": null,
      "death_100k": 186,
      "incidence": 12801,
      "id": 6,
      "fips": "06",
      "name": "California",
      "state_level_community_transmission": "substantial",
      "us_trend_new_case": 20976,
      "us_trend_new_death": 291,
      "us_trend_maxdate": "2021-11-29"
    },
    {
      "abbr": "CO",
      "tot_cases": 826815,
      "tot_cases_last_24_hours": 0,
      "conf_cases": 757584,
      "prob_cases": 69231,
      "new_cases07": 15002,
      "new_deaths07": 200,
      "Seven_day_avg_new_cases_per_100k": 37.2,
      "Seven_day_avg_new_deaths_per_100k": 0.5,
      "Seven_day_cum_new_cases_per_100k": 260.5,
      "Seven_day_cum_new_deaths_per_100k": 3.5,
      "tot_death": 9151,
      "tot_death_last_24_hours": 0,
      "conf_death": 8137,
      "prob_death": 1014,
      "death_100k": 158,
      "incidence": 14358,
      "id": 8,
      "fips": "08",
      "name": "Colorado",
      "state_level_community_transmission": "high",
      "us_trend_new_case": 4956,
      "us_trend_new_death": 51,
      "us_trend_maxdate": "2021-11-29"
    },
    {
      "abbr": "CT",
      "tot_cases": 420785,
      "tot_cases_last_24_hours": 0,
      "conf_cases": 382173,
      "prob_cases": 38612,
      "new_cases07": 5807,
      "new_deaths07": 12,
      "Seven_day_avg_new_cases_per_100k": 23.3,
      "Seven_day_avg_new_deaths_per_100k": 0.1,
      "Seven_day_cum_new_cases_per_100k": 162.9,
      "Seven_day_cum_new_deaths_per_100k": 0.3,
      "tot_death": 8864,
      "tot_death_last_24_hours": 0,
      "conf_death": 7263,
      "prob_death": 1601,
      "death_100k": 248,
      "incidence": 11802,
      "id": 9,
      "fips": "09",
      "name": "Connecticut",
      "state_level_community_transmission": "high",
      "us_trend_new_case": 2312,
      "us_trend_new_death": -1,
      "us_trend_maxdate": "2021-11-29"
    },
    {
      "abbr": "DC",
      "tot_cases": 66857,
      "tot_cases_last_24_hours": 0,
      "conf_cases": 0,
      "prob_cases": 0,
      "new_cases07": 510,
      "new_deaths07": 0,
      "Seven_day_avg_new_cases_per_100k": 10.3,
      "Seven_day_avg_new_deaths_per_100k": 0,
      "Seven_day_cum_new_cases_per_100k": 72.3,
      "Seven_day_cum_new_deaths_per_100k": 0,
      "tot_death": 1196,
      "tot_death_last_24_hours": 0,
      "conf_death": null,
      "prob_death": null,
      "death_100k": 169,
      "incidence": 9473,
      "id": 11,
      "fips": "11",
      "name": "District of Columbia",
      "state_level_community_transmission": "substantial",
      "us_trend_new_case": 347,
      "us_trend_new_death": 0,
      "us_trend_maxdate": "2021-11-29"
    },
    {
      "abbr": "DE",
      "tot_cases": 152904,
      "tot_cases_last_24_hours": 0,
      "conf_cases": 139887,
      "prob_cases": 13017,
      "new_cases07": 2279,
      "new_deaths07": 14,
      "Seven_day_avg_new_cases_per_100k": 33.4,
      "Seven_day_avg_new_deaths_per_100k": 0.2,
      "Seven_day_cum_new_cases_per_100k": 234,
      "Seven_day_cum_new_deaths_per_100k": 1.4,
      "tot_death": 2173,
      "tot_death_last_24_hours": 0,
      "conf_death": 1990,
      "prob_death": 183,
      "death_100k": 223,
      "incidence": 15702,
      "id": 10,
      "fips": "10",
      "name": "Delaware",
      "state_level_community_transmission": "high",
      "us_trend_new_case": 234,
      "us_trend_new_death": 0,
      "us_trend_maxdate": "2021-11-29"
    },
    {
      "abbr": "FL",
      "tot_cases": 3691420,
      "tot_cases_last_24_hours": 0,
      "conf_cases": 0,
      "prob_cases": 0,
      "new_cases07": 8852,
      "new_deaths07": 11,
      "Seven_day_avg_new_cases_per_100k": 5.9,
      "Seven_day_avg_new_deaths_per_100k": 0,
      "Seven_day_cum_new_cases_per_100k": 41.2,
      "Seven_day_cum_new_deaths_per_100k": 0.1,
      "tot_death": 61539,
      "tot_death_last_24_hours": 0,
      "conf_death": null,
      "prob_death": null,
      "death_100k": 286,
      "incidence": 17187,
      "id": 12,
      "fips": "12",
      "name": "Florida",
      "state_level_community_transmission": "moderate",
      "us_trend_new_case": 1632,
      "us_trend_new_death": 1,
      "us_trend_maxdate": "2021-11-29"
    },
    {
      "abbr": "FSM",
      "tot_cases": 7,
      "tot_cases_last_24_hours": 0,
      "conf_cases": 7,
      "prob_cases": 0,
      "new_cases07": 0,
      "new_deaths07": 0,
      "Seven_day_avg_new_cases_per_100k": 0,
      "Seven_day_avg_new_deaths_per_100k": 0,
      "Seven_day_cum_new_cases_per_100k": 0,
      "Seven_day_cum_new_deaths_per_100k": 0,
      "tot_death": 0,
      "tot_death_last_24_hours": 0,
      "conf_death": null,
      "prob_death": null,
      "death_100k": null,
      "incidence": 7,
      "id": 64,
      "fips": "64",
      "name": "Federated States of Micronesia",
      "state_level_community_transmission": "",
      "us_trend_new_case": 0,
      "us_trend_new_death": 0,
      "us_trend_maxdate": "2021-11-29"
    },
    {
      "abbr": "GA",
      "tot_cases": 1662995,
      "tot_cases_last_24_hours": 0,
      "conf_cases": 1284354,
      "prob_cases": 378641,
      "new_cases07": 6003,
      "new_deaths07": 235,
      "Seven_day_avg_new_cases_per_100k": 8.1,
      "Seven_day_avg_new_deaths_per_100k": 0.3,
      "Seven_day_cum_new_cases_per_100k": 56.5,
      "Seven_day_cum_new_deaths_per_100k": 2.2,
      "tot_death": 30471,
      "tot_death_last_24_hours": 0,
      "conf_death": 25704,
      "prob_death": 4767,
      "death_100k": 286,
      "incidence": 15663,
      "id": 13,
      "fips": "13",
      "name": "Georgia",
      "state_level_community_transmission": "substantial",
      "us_trend_new_case": 704,
      "us_trend_new_death": 113,
      "us_trend_maxdate": "2021-11-29"
    },
    {
      "abbr": "GU",
      "tot_cases": 19199,
      "tot_cases_last_24_hours": 0,
      "conf_cases": 0,
      "prob_cases": 0,
      "new_cases07": 82,
      "new_deaths07": 0,
      "Seven_day_avg_new_cases_per_100k": 7,
      "Seven_day_avg_new_deaths_per_100k": 0,
      "Seven_day_cum_new_cases_per_100k": 48.7,
      "Seven_day_cum_new_deaths_per_100k": 0,
      "tot_death": 263,
      "tot_death_last_24_hours": 0,
      "conf_death": null,
      "prob_death": null,
      "death_100k": 156,
      "incidence": 11395,
      "id": 66,
      "fips": "66",
      "name": "Guam",
      "state_level_community_transmission": "moderate",
      "us_trend_new_case": 20,
      "us_trend_new_death": 0,
      "us_trend_maxdate": "2021-11-29"
    },
    {
      "abbr": "HI",
      "tot_cases": 84685,
      "tot_cases_last_24_hours": 0,
      "conf_cases": 0,
      "prob_cases": 0,
      "new_cases07": 601,
      "new_deaths07": 16,
      "Seven_day_avg_new_cases_per_100k": 6.1,
      "Seven_day_avg_new_deaths_per_100k": 0.2,
      "Seven_day_cum_new_cases_per_100k": 42.5,
      "Seven_day_cum_new_deaths_per_100k": 1.1,
      "tot_death": 1007,
      "tot_death_last_24_hours": 0,
      "conf_death": null,
      "prob_death": null,
      "death_100k": 71,
      "incidence": 5981,
      "id": 15,
      "fips": "15",
      "name": "Hawaii",
      "state_level_community_transmission": "moderate",
      "us_trend_new_case": 70,
      "us_trend_new_death": 0,
      "us_trend_maxdate": "2021-11-29"
    },
    {
      "abbr": "IA",
      "tot_cases": 525458,
      "tot_cases_last_24_hours": 0,
      "conf_cases": 0,
      "prob_cases": 0,
      "new_cases07": 8551,
      "new_deaths07": 86,
      "Seven_day_avg_new_cases_per_100k": 38.7,
      "Seven_day_avg_new_deaths_per_100k": 0.4,
      "Seven_day_cum_new_cases_per_100k": 271,
      "Seven_day_cum_new_deaths_per_100k": 2.7,
      "tot_death": 7354,
      "tot_death_last_24_hours": 0,
      "conf_death": null,
      "prob_death": null,
      "death_100k": 233,
      "incidence": 16654,
      "id": 19,
      "fips": "19",
      "name": "Iowa",
      "state_level_community_transmission": "high",
      "us_trend_new_case": 2600,
      "us_trend_new_death": 0,
      "us_trend_maxdate": "2021-11-29"
    },
    {
      "abbr": "ID",
      "tot_cases": 306209,
      "tot_cases_last_24_hours": 0,
      "conf_cases": 242815,
      "prob_cases": 63394,
      "new_cases07": 2281,
      "new_deaths07": 59,
      "Seven_day_avg_new_cases_per_100k": 18.2,
      "Seven_day_avg_new_deaths_per_100k": 0.5,
      "Seven_day_cum_new_cases_per_100k": 127.6,
      "Seven_day_cum_new_deaths_per_100k": 3.3,
      "tot_death": 3921,
      "tot_death_last_24_hours": 0,
      "conf_death": 3234,
      "prob_death": 687,
      "death_100k": 219,
      "incidence": 17135,
      "id": 16,
      "fips": "16",
      "name": "Idaho",
      "state_level_community_transmission": "high",
      "us_trend_new_case": 447,
      "us_trend_new_death": 22,
      "us_trend_maxdate": "2021-11-29"
    },
    {
      "abbr": "IL",
      "tot_cases": 1804161,
      "tot_cases_last_24_hours": 0,
      "conf_cases": 1804161,
      "prob_cases": 0,
      "new_cases07": 28908,
      "new_deaths07": 134,
      "Seven_day_avg_new_cases_per_100k": 32.6,
      "Seven_day_avg_new_deaths_per_100k": 0.2,
      "Seven_day_cum_new_cases_per_100k": 228.1,
      "Seven_day_cum_new_deaths_per_100k": 1.1,
      "tot_death": 29349,
      "tot_death_last_24_hours": 0,
      "conf_death": 26391,
      "prob_death": 2958,
      "death_100k": 231,
      "incidence": 14238,
      "id": 17,
      "fips": "17",
      "name": "Illinois",
      "state_level_community_transmission": "high",
      "us_trend_new_case": 3853,
      "us_trend_new_death": 91,
      "us_trend_maxdate": "2021-11-29"
    },
    {
      "abbr": "IN",
      "tot_cases": 1097128,
      "tot_cases_last_24_hours": 0,
      "conf_cases": 0,
      "prob_cases": 0,
      "new_cases07": 19756,
      "new_deaths07": 122,
      "Seven_day_avg_new_cases_per_100k": 41.9,
      "Seven_day_avg_new_deaths_per_100k": 0.3,
      "Seven_day_cum_new_cases_per_100k": 293.5,
      "Seven_day_cum_new_deaths_per_100k": 1.8,
      "tot_death": 17438,
      "tot_death_last_24_hours": 0,
      "conf_death": 16853,
      "prob_death": 585,
      "death_100k": 259,
      "incidence": 16297,
      "id": 18,
      "fips": "18",
      "name": "Indiana",
      "state_level_community_transmission": "high",
      "us_trend_new_case": 2528,
      "us_trend_new_death": 52,
      "us_trend_maxdate": "2021-11-29"
    },
    {
      "abbr": "KS",
      "tot_cases": 465290,
      "tot_cases_last_24_hours": 0,
      "conf_cases": 363434,
      "prob_cases": 101856,
      "new_cases07": 7070,
      "new_deaths07": 43,
      "Seven_day_avg_new_cases_per_100k": 34.7,
      "Seven_day_avg_new_deaths_per_100k": 0.2,
      "Seven_day_cum_new_cases_per_100k": 242.7,
      "Seven_day_cum_new_deaths_per_100k": 1.5,
      "tot_death": 6686,
      "tot_death_last_24_hours": 0,
      "conf_death": null,
      "prob_death": null,
      "death_100k": 229,
      "incidence": 15971,
      "id": 20,
      "fips": "20",
      "name": "Kansas",
      "state_level_community_transmission": "high",
      "us_trend_new_case": 827,
      "us_trend_new_death": 13,
      "us_trend_maxdate": "2021-11-29"
    },
    {
      "abbr": "KY",
      "tot_cases": 783409,
      "tot_cases_last_24_hours": 0,
      "conf_cases": 554501,
      "prob_cases": 228908,
      "new_cases07": 9405,
      "new_deaths07": 153,
      "Seven_day_avg_new_cases_per_100k": 30.1,
      "Seven_day_avg_new_deaths_per_100k": 0.5,
      "Seven_day_cum_new_cases_per_100k": 210.5,
      "Seven_day_cum_new_deaths_per_100k": 3.4,
      "tot_death": 10913,
      "tot_death_last_24_hours": 0,
      "conf_death": 9606,
      "prob_death": 1307,
      "death_100k": 244,
      "incidence": 17535,
      "id": 21,
      "fips": "21",
      "name": "Kentucky",
      "state_level_community_transmission": "high",
      "us_trend_new_case": 2728,
      "us_trend_new_death": 61,
      "us_trend_maxdate": "2021-11-29"
    },
    {
      "abbr": "LA",
      "tot_cases": 770305,
      "tot_cases_last_24_hours": 0,
      "conf_cases": 0,
      "prob_cases": 0,
      "new_cases07": 2264,
      "new_deaths07": 40,
      "Seven_day_avg_new_cases_per_100k": 7,
      "Seven_day_avg_new_deaths_per_100k": 0.1,
      "Seven_day_cum_new_cases_per_100k": 48.7,
      "Seven_day_cum_new_deaths_per_100k": 0.9,
      "tot_death": 14794,
      "tot_death_last_24_hours": 0,
      "conf_death": 12882,
      "prob_death": 1912,
      "death_100k": 318,
      "incidence": 16570,
      "id": 22,
      "fips": "22",
      "name": "Louisiana",
      "state_level_community_transmission": "moderate",
      "us_trend_new_case": 254,
      "us_trend_new_death": 17,
      "us_trend_maxdate": "2021-11-29"
    },
    {
      "abbr": "MA",
      "tot_cases": 915495,
      "tot_cases_last_24_hours": 0,
      "conf_cases": 852527,
      "prob_cases": 62968,
      "new_cases07": 17621,
      "new_deaths07": 89,
      "Seven_day_avg_new_cases_per_100k": 36.5,
      "Seven_day_avg_new_deaths_per_100k": 0.2,
      "Seven_day_cum_new_cases_per_100k": 255.7,
      "Seven_day_cum_new_deaths_per_100k": 1.3,
      "tot_death": 19373,
      "tot_death_last_24_hours": 0,
      "conf_death": 18960,
      "prob_death": 413,
      "death_100k": 281,
      "incidence": 13282,
      "id": 25,
      "fips": "25",
      "name": "Massachusetts",
      "state_level_community_transmission": "high",
      "us_trend_new_case": 5790,
      "us_trend_new_death": 22,
      "us_trend_maxdate": "2021-11-29"
    },
    {
      "abbr": "MD",
      "tot_cases": 586143,
      "tot_cases_last_24_hours": 0,
      "conf_cases": 0,
      "prob_cases": 0,
      "new_cases07": 6552,
      "new_deaths07": 61,
      "Seven_day_avg_new_cases_per_100k": 15.5,
      "Seven_day_avg_new_deaths_per_100k": 0.1,
      "Seven_day_cum_new_cases_per_100k": 108.4,
      "Seven_day_cum_new_deaths_per_100k": 1,
      "tot_death": 11206,
      "tot_death_last_24_hours": 0,
      "conf_death": 10973,
      "prob_death": 233,
      "death_100k": 185,
      "incidence": 9695,
      "id": 24,
      "fips": "24",
      "name": "Maryland",
      "state_level_community_transmission": "high",
      "us_trend_new_case": 2006,
      "us_trend_new_death": 20,
      "us_trend_maxdate": "2021-11-29"
    },
    {
      "abbr": "ME",
      "tot_cases": 119662,
      "tot_cases_last_24_hours": 0,
      "conf_cases": 85510,
      "prob_cases": 34152,
      "new_cases07": 2715,
      "new_deaths07": 24,
      "Seven_day_avg_new_cases_per_100k": 28.9,
      "Seven_day_avg_new_deaths_per_100k": 0.3,
      "Seven_day_cum_new_cases_per_100k": 202,
      "Seven_day_cum_new_deaths_per_100k": 1.8,
      "tot_death": 1324,
      "tot_death_last_24_hours": 0,
      "conf_death": 1221,
      "prob_death": 103,
      "death_100k": 98,
      "incidence": 8902,
      "id": 23,
      "fips": "23",
      "name": "Maine",
      "state_level_community_transmission": "high",
      "us_trend_new_case": 1173,
      "us_trend_new_death": 21,
      "us_trend_maxdate": "2021-11-29"
    },
    {
      "abbr": "MI",
      "tot_cases": 1475053,
      "tot_cases_last_24_hours": 0,
      "conf_cases": 1301593,
      "prob_cases": 173460,
      "new_cases07": 47862,
      "new_deaths07": 271,
      "Seven_day_avg_new_cases_per_100k": 68.5,
      "Seven_day_avg_new_deaths_per_100k": 0.4,
      "Seven_day_cum_new_cases_per_100k": 479.3,
      "Seven_day_cum_new_deaths_per_100k": 2.7,
      "tot_death": 25399,
      "tot_death_last_24_hours": 0,
      "conf_death": 23732,
      "prob_death": 1667,
      "death_100k": 254,
      "incidence": 14770,
      "id": 26,
      "fips": "26",
      "name": "Michigan",
      "state_level_community_transmission": "high",
      "us_trend_new_case": 5571,
      "us_trend_new_death": 98,
      "us_trend_maxdate": "2021-11-29"
    },
    {
      "abbr": "MN",
      "tot_cases": 899739,
      "tot_cases_last_24_hours": 0,
      "conf_cases": 0,
      "prob_cases": 0,
      "new_cases07": 23822,
      "new_deaths07": 190,
      "Seven_day_avg_new_cases_per_100k": 60.3,
      "Seven_day_avg_new_deaths_per_100k": 0.5,
      "Seven_day_cum_new_cases_per_100k": 422.4,
      "Seven_day_cum_new_deaths_per_100k": 3.4,
      "tot_death": 9506,
      "tot_death_last_24_hours": 0,
      "conf_death": 8827,
      "prob_death": 679,
      "death_100k": 168,
      "incidence": 15954,
      "id": 27,
      "fips": "27",
      "name": "Minnesota",
      "state_level_community_transmission": "high",
      "us_trend_new_case": 4510,
      "us_trend_new_death": 44,
      "us_trend_maxdate": "2021-11-29"
    },
    {
      "abbr": "MO",
      "tot_cases": 907353,
      "tot_cases_last_24_hours": 0,
      "conf_cases": 0,
      "prob_cases": 0,
      "new_cases07": 11306,
      "new_deaths07": 107,
      "Seven_day_avg_new_cases_per_100k": 26.3,
      "Seven_day_avg_new_deaths_per_100k": 0.3,
      "Seven_day_cum_new_cases_per_100k": 184.2,
      "Seven_day_cum_new_deaths_per_100k": 1.7,
      "tot_death": 15434,
      "tot_death_last_24_hours": 0,
      "conf_death": null,
      "prob_death": null,
      "death_100k": 251,
      "incidence": 14784,
      "id": 29,
      "fips": "29",
      "name": "Missouri",
      "state_level_community_transmission": "high",
      "us_trend_new_case": 2369,
      "us_trend_new_death": 91,
      "us_trend_maxdate": "2021-11-29"
    },
    {
      "abbr": "MP",
      "tot_cases": 395,
      "tot_cases_last_24_hours": 0,
      "conf_cases": 395,
      "prob_cases": 0,
      "new_cases07": 0,
      "new_deaths07": 0,
      "Seven_day_avg_new_cases_per_100k": 0,
      "Seven_day_avg_new_deaths_per_100k": 0,
      "Seven_day_cum_new_cases_per_100k": 0,
      "Seven_day_cum_new_deaths_per_100k": 0,
      "tot_death": 3,
      "tot_death_last_24_hours": 0,
      "conf_death": 3,
      "prob_death": 0,
      "death_100k": 5,
      "incidence": 762,
      "id": 69,
      "fips": "69",
      "name": "Northern Mariana Islands",
      "state_level_community_transmission": "low",
      "us_trend_new_case": 0,
      "us_trend_new_death": 0,
      "us_trend_maxdate": "2021-11-29"
    },
    {
      "abbr": "MS",
      "tot_cases": 513622,
      "tot_cases_last_24_hours": 0,
      "conf_cases": 293999,
      "prob_cases": 219623,
      "new_cases07": 1687,
      "new_deaths07": 10,
      "Seven_day_avg_new_cases_per_100k": 8.1,
      "Seven_day_avg_new_deaths_per_100k": 0.1,
      "Seven_day_cum_new_cases_per_100k": 56.7,
      "Seven_day_cum_new_deaths_per_100k": 0.3,
      "tot_death": 10264,
      "tot_death_last_24_hours": 0,
      "conf_death": 6871,
      "prob_death": 3393,
      "death_100k": 344,
      "incidence": 17258,
      "id": 28,
      "fips": "28",
      "name": "Mississippi",
      "state_level_community_transmission": "substantial",
      "us_trend_new_case": 202,
      "us_trend_new_death": 1,
      "us_trend_maxdate": "2021-11-29"
    },
    {
      "abbr": "MT",
      "tot_cases": 190424,
      "tot_cases_last_24_hours": 0,
      "conf_cases": 157894,
      "prob_cases": 32530,
      "new_cases07": 1919,
      "new_deaths07": 71,
      "Seven_day_avg_new_cases_per_100k": 25.7,
      "Seven_day_avg_new_deaths_per_100k": 1,
      "Seven_day_cum_new_cases_per_100k": 179.6,
      "Seven_day_cum_new_deaths_per_100k": 6.6,
      "tot_death": 2638,
      "tot_death_last_24_hours": 0,
      "conf_death": 2638,
      "prob_death": 0,
      "death_100k": 246,
      "incidence": 17817,
      "id": 30,
      "fips": "30",
      "name": "Montana",
      "state_level_community_transmission": "high",
      "us_trend_new_case": 353,
      "us_trend_new_death": 7,
      "us_trend_maxdate": "2021-11-29"
    },
    {
      "abbr": "NC",
      "tot_cases": 1532250,
      "tot_cases_last_24_hours": 0,
      "conf_cases": 1287820,
      "prob_cases": 244430,
      "new_cases07": 11779,
      "new_deaths07": 84,
      "Seven_day_avg_new_cases_per_100k": 16,
      "Seven_day_avg_new_deaths_per_100k": 0.1,
      "Seven_day_cum_new_cases_per_100k": 112.3,
      "Seven_day_cum_new_deaths_per_100k": 0.8,
      "tot_death": 18714,
      "tot_death_last_24_hours": 0,
      "conf_death": 16470,
      "prob_death": 2244,
      "death_100k": 178,
      "incidence": 14609,
      "id": 37,
      "fips": "37",
      "name": "North Carolina",
      "state_level_community_transmission": "high",
      "us_trend_new_case": 1636,
      "us_trend_new_death": 38,
      "us_trend_maxdate": "2021-11-29"
    },
    {
      "abbr": "ND",
      "tot_cases": 162294,
      "tot_cases_last_24_hours": 0,
      "conf_cases": 134840,
      "prob_cases": 27454,
      "new_cases07": 2921,
      "new_deaths07": 31,
      "Seven_day_avg_new_cases_per_100k": 54.8,
      "Seven_day_avg_new_deaths_per_100k": 0.6,
      "Seven_day_cum_new_cases_per_100k": 383.3,
      "Seven_day_cum_new_deaths_per_100k": 4.1,
      "tot_death": 1892,
      "tot_death_last_24_hours": 0,
      "conf_death": null,
      "prob_death": null,
      "death_100k": 248,
      "incidence": 21297,
      "id": 38,
      "fips": "38",
      "name": "North Dakota",
      "state_level_community_transmission": "high",
      "us_trend_new_case": 992,
      "us_trend_new_death": 15,
      "us_trend_maxdate": "2021-11-29"
    },
    {
      "abbr": "NE",
      "tot_cases": 309828,
      "tot_cases_last_24_hours": 0,
      "conf_cases": 232625,
      "prob_cases": 77203,
      "new_cases07": 5396,
      "new_deaths07": 43,
      "Seven_day_avg_new_cases_per_100k": 39.9,
      "Seven_day_avg_new_deaths_per_100k": 0.3,
      "Seven_day_cum_new_cases_per_100k": 279,
      "Seven_day_cum_new_deaths_per_100k": 2.2,
      "tot_death": 3155,
      "tot_death_last_24_hours": 0,
      "conf_death": 2643,
      "prob_death": 512,
      "death_100k": 163,
      "incidence": 16017,
      "id": 31,
      "fips": "31",
      "name": "Nebraska",
      "state_level_community_transmission": "high",
      "us_trend_new_case": 1932,
      "us_trend_new_death": 9,
      "us_trend_maxdate": "2021-11-29"
    },
    {
      "abbr": "NH",
      "tot_cases": 160287,
      "tot_cases_last_24_hours": 0,
      "conf_cases": 0,
      "prob_cases": 0,
      "new_cases07": 6353,
      "new_deaths07": 22,
      "Seven_day_avg_new_cases_per_100k": 66.8,
      "Seven_day_avg_new_deaths_per_100k": 0.2,
      "Seven_day_cum_new_cases_per_100k": 467.2,
      "Seven_day_cum_new_deaths_per_100k": 1.6,
      "tot_death": 1694,
      "tot_death_last_24_hours": 0,
      "conf_death": null,
      "prob_death": null,
      "death_100k": 124,
      "incidence": 11788,
      "id": 33,
      "fips": "33",
      "name": "New Hampshire",
      "state_level_community_transmission": "high",
      "us_trend_new_case": 916,
      "us_trend_new_death": 11,
      "us_trend_maxdate": "2021-11-29"
    },
    {
      "abbr": "NJ",
      "tot_cases": 1249454,
      "tot_cases_last_24_hours": 0,
      "conf_cases": 1084414,
      "prob_cases": 165040,
      "new_cases07": 15943,
      "new_deaths07": 83,
      "Seven_day_avg_new_cases_per_100k": 25.6,
      "Seven_day_avg_new_deaths_per_100k": 0.1,
      "Seven_day_cum_new_cases_per_100k": 179.5,
      "Seven_day_cum_new_deaths_per_100k": 0.9,
      "tot_death": 28348,
      "tot_death_last_24_hours": 0,
      "conf_death": 25521,
      "prob_death": 2827,
      "death_100k": 319,
      "incidence": 14067,
      "id": 34,
      "fips": "34",
      "name": "New Jersey",
      "state_level_community_transmission": "high",
      "us_trend_new_case": 2241,
      "us_trend_new_death": 9,
      "us_trend_maxdate": "2021-11-29"
    },
    {
      "abbr": "NM",
      "tot_cases": 313139,
      "tot_cases_last_24_hours": 0,
      "conf_cases": 0,
      "prob_cases": 0,
      "new_cases07": 7560,
      "new_deaths07": 78,
      "Seven_day_avg_new_cases_per_100k": 51.5,
      "Seven_day_avg_new_deaths_per_100k": 0.5,
      "Seven_day_cum_new_cases_per_100k": 360.5,
      "Seven_day_cum_new_deaths_per_100k": 3.7,
      "tot_death": 5355,
      "tot_death_last_24_hours": 0,
      "conf_death": null,
      "prob_death": null,
      "death_100k": 255,
      "incidence": 14934,
      "id": 35,
      "fips": "35",
      "name": "New Mexico",
      "state_level_community_transmission": "high",
      "us_trend_new_case": 1012,
      "us_trend_new_death": 45,
      "us_trend_maxdate": "2021-11-29"
    },
    {
      "abbr": "NV",
      "tot_cases": 469743,
      "tot_cases_last_24_hours": 0,
      "conf_cases": 456803,
      "prob_cases": 12940,
      "new_cases07": 3343,
      "new_deaths07": 55,
      "Seven_day_avg_new_cases_per_100k": 15.5,
      "Seven_day_avg_new_deaths_per_100k": 0.3,
      "Seven_day_cum_new_cases_per_100k": 108.5,
      "Seven_day_cum_new_deaths_per_100k": 1.8,
      "tot_death": 7985,
      "tot_death_last_24_hours": 0,
      "conf_death": null,
      "prob_death": null,
      "death_100k": 259,
      "incidence": 15251,
      "id": 32,
      "fips": "32",
      "name": "Nevada",
      "state_level_community_transmission": "high",
      "us_trend_new_case": 397,
      "us_trend_new_death": 13,
      "us_trend_maxdate": "2021-11-29"
    },
    {
      "abbr": "NY",
      "tot_cases": 1564336,
      "tot_cases_last_24_hours": 0,
      "conf_cases": 0,
      "prob_cases": 0,
      "new_cases07": 33273,
      "new_deaths07": 191,
      "Seven_day_avg_new_cases_per_100k": 43,
      "Seven_day_avg_new_deaths_per_100k": 0.3,
      "Seven_day_cum_new_cases_per_100k": 301,
      "Seven_day_cum_new_deaths_per_100k": 1.7,
      "tot_death": 22185,
      "tot_death_last_24_hours": 0,
      "conf_death": null,
      "prob_death": null,
      "death_100k": 200,
      "incidence": 14151,
      "id": 36,
      "fips": "36",
      "name": "New York",
      "state_level_community_transmission": "high",
      "us_trend_new_case": 3994,
      "us_trend_new_death": 35,
      "us_trend_maxdate": "2021-11-29"
    },
    {
      "abbr": "NYC",
      "tot_cases": 1159600,
      "tot_cases_last_24_hours": 0,
      "conf_cases": 944791,
      "prob_cases": 214809,
      "new_cases07": 10456,
      "new_deaths07": 70,
      "Seven_day_avg_new_cases_per_100k": 17.8,
      "Seven_day_avg_new_deaths_per_100k": 0.1,
      "Seven_day_cum_new_cases_per_100k": 124.5,
      "Seven_day_cum_new_deaths_per_100k": 0.8,
      "tot_death": 34828,
      "tot_death_last_24_hours": 0,
      "conf_death": 29643,
      "prob_death": 5185,
      "death_100k": 414,
      "incidence": 13807,
      "id": 57,
      "fips": "57",
      "name": "New York City",
      "state_level_community_transmission": "null",
      "us_trend_new_case": 1670,
      "us_trend_new_death": 20,
      "us_trend_maxdate": "2021-11-29"
    },
    {
      "abbr": "OH",
      "tot_cases": 1683472,
      "tot_cases_last_24_hours": 0,
      "conf_cases": 1345285,
      "prob_cases": 338187,
      "new_cases07": 36235,
      "new_deaths07": 420,
      "Seven_day_avg_new_cases_per_100k": 44.3,
      "Seven_day_avg_new_deaths_per_100k": 0.5,
      "Seven_day_cum_new_cases_per_100k": 310,
      "Seven_day_cum_new_deaths_per_100k": 3.6,
      "tot_death": 26483,
      "tot_death_last_24_hours": 0,
      "conf_death": 26483,
      "prob_death": 0,
      "death_100k": 226,
      "incidence": 14402,
      "id": 39,
      "fips": "39",
      "name": "Ohio",
      "state_level_community_transmission": "high",
      "us_trend_new_case": 5731,
      "us_trend_new_death": 0,
      "us_trend_maxdate": "2021-11-29"
    },
    {
      "abbr": "OK",
      "tot_cases": 666927,
      "tot_cases_last_24_hours": 0,
      "conf_cases": 504357,
      "prob_cases": 162570,
      "new_cases07": 7342,
      "new_deaths07": 160,
      "Seven_day_avg_new_cases_per_100k": 26.5,
      "Seven_day_avg_new_deaths_per_100k": 0.6,
      "Seven_day_cum_new_cases_per_100k": 185.6,
      "Seven_day_cum_new_deaths_per_100k": 4,
      "tot_death": 11267,
      "tot_death_last_24_hours": 0,
      "conf_death": 8577,
      "prob_death": 2690,
      "death_100k": 284,
      "incidence": 16854,
      "id": 40,
      "fips": "40",
      "name": "Oklahoma",
      "state_level_community_transmission": "high",
      "us_trend_new_case": 758,
      "us_trend_new_death": 44,
      "us_trend_maxdate": "2021-11-29"
    },
    {
      "abbr": "OR",
      "tot_cases": 390066,
      "tot_cases_last_24_hours": 0,
      "conf_cases": 390066,
      "prob_cases": 0,
      "new_cases07": 4276,
      "new_deaths07": 125,
      "Seven_day_avg_new_cases_per_100k": 14.5,
      "Seven_day_avg_new_deaths_per_100k": 0.4,
      "Seven_day_cum_new_cases_per_100k": 101.4,
      "Seven_day_cum_new_deaths_per_100k": 3,
      "tot_death": 5142,
      "tot_death_last_24_hours": 0,
      "conf_death": 5142,
      "prob_death": 0,
      "death_100k": 121,
      "incidence": 9248,
      "id": 41,
      "fips": "41",
      "name": "Oregon",
      "state_level_community_transmission": "high",
      "us_trend_new_case": 517,
      "us_trend_new_death": 26,
      "us_trend_maxdate": "2021-11-29"
    },
    {
      "abbr": "PA",
      "tot_cases": 1731154,
      "tot_cases_last_24_hours": 0,
      "conf_cases": 1426258,
      "prob_cases": 304896,
      "new_cases07": 39381,
      "new_deaths07": 377,
      "Seven_day_avg_new_cases_per_100k": 44,
      "Seven_day_avg_new_deaths_per_100k": 0.4,
      "Seven_day_cum_new_cases_per_100k": 307.6,
      "Seven_day_cum_new_deaths_per_100k": 2.9,
      "tot_death": 33308,
      "tot_death_last_24_hours": 0,
      "conf_death": null,
      "prob_death": null,
      "death_100k": 260,
      "incidence": 13522,
      "id": 42,
      "fips": "42",
      "name": "Pennsylvania",
      "state_level_community_transmission": "high",
      "us_trend_new_case": 5252,
      "us_trend_new_death": 25,
      "us_trend_maxdate": "2021-11-29"
    },
    {
      "abbr": "PR",
      "tot_cases": 187999,
      "tot_cases_last_24_hours": 0,
      "conf_cases": 153934,
      "prob_cases": 34065,
      "new_cases07": 514,
      "new_deaths07": 5,
      "Seven_day_avg_new_cases_per_100k": 2.3,
      "Seven_day_avg_new_deaths_per_100k": 0,
      "Seven_day_cum_new_cases_per_100k": 16.1,
      "Seven_day_cum_new_deaths_per_100k": 0.2,
      "tot_death": 3269,
      "tot_death_last_24_hours": 0,
      "conf_death": 2786,
      "prob_death": 483,
      "death_100k": 102,
      "incidence": 5887,
      "id": 72,
      "fips": "72",
      "name": "Puerto Rico",
      "state_level_community_transmission": "moderate",
      "us_trend_new_case": 63,
      "us_trend_new_death": 0,
      "us_trend_maxdate": "2021-11-29"
    },
    {
      "abbr": "PW",
      "tot_cases": 10,
      "tot_cases_last_24_hours": 0,
      "conf_cases": 0,
      "prob_cases": 0,
      "new_cases07": 0,
      "new_deaths07": 0,
      "Seven_day_avg_new_cases_per_100k": 0,
      "Seven_day_avg_new_deaths_per_100k": 0,
      "Seven_day_cum_new_cases_per_100k": 0,
      "Seven_day_cum_new_deaths_per_100k": 0,
      "tot_death": 0,
      "tot_death_last_24_hours": 0,
      "conf_death": null,
      "prob_death": null,
      "death_100k": null,
      "incidence": 46,
      "id": 70,
      "fips": "70",
      "name": "Palau",
      "state_level_community_transmission": "low",
      "us_trend_new_case": 0,
      "us_trend_new_death": 0,
      "us_trend_maxdate": "2021-11-29"
    },
    {
      "abbr": "RI",
      "tot_cases": 190975,
      "tot_cases_last_24_hours": 0,
      "conf_cases": 0,
      "prob_cases": 0,
      "new_cases07": 3444,
      "new_deaths07": 14,
      "Seven_day_avg_new_cases_per_100k": 46.4,
      "Seven_day_avg_new_deaths_per_100k": 0.2,
      "Seven_day_cum_new_cases_per_100k": 325.1,
      "Seven_day_cum_new_deaths_per_100k": 1.3,
      "tot_death": 2927,
      "tot_death_last_24_hours": 0,
      "conf_death": null,
      "prob_death": null,
      "death_100k": 276,
      "incidence": 18027,
      "id": 44,
      "fips": "44",
      "name": "Rhode Island",
      "state_level_community_transmission": "high",
      "us_trend_new_case": 486,
      "us_trend_new_death": 12,
      "us_trend_maxdate": "2021-11-29"
    },
    {
      "abbr": "RMI",
      "tot_cases": 4,
      "tot_cases_last_24_hours": 0,
      "conf_cases": 4,
      "prob_cases": 0,
      "new_cases07": 0,
      "new_deaths07": 0,
      "Seven_day_avg_new_cases_per_100k": 0,
      "Seven_day_avg_new_deaths_per_100k": 0,
      "Seven_day_cum_new_cases_per_100k": 0,
      "Seven_day_cum_new_deaths_per_100k": 0,
      "tot_death": 0,
      "tot_death_last_24_hours": 0,
      "conf_death": null,
      "prob_death": null,
      "death_100k": null,
      "incidence": 5,
      "id": 68,
      "fips": "68",
      "name": "Republic of Marshall Islands",
      "state_level_community_transmission": "low",
      "us_trend_new_case": 0,
      "us_trend_new_death": 0,
      "us_trend_maxdate": "2021-11-29"
    },
    {
      "abbr": "SC",
      "tot_cases": 917836,
      "tot_cases_last_24_hours": 0,
      "conf_cases": 734559,
      "prob_cases": 183277,
      "new_cases07": 3924,
      "new_deaths07": 81,
      "Seven_day_avg_new_cases_per_100k": 10.9,
      "Seven_day_avg_new_deaths_per_100k": 0.2,
      "Seven_day_cum_new_cases_per_100k": 76.2,
      "Seven_day_cum_new_deaths_per_100k": 1.6,
      "tot_death": 14209,
      "tot_death_last_24_hours": 0,
      "conf_death": null,
      "prob_death": null,
      "death_100k": 275,
      "incidence": 17826,
      "id": 45,
      "fips": "45",
      "name": "South Carolina",
      "state_level_community_transmission": "substantial",
      "us_trend_new_case": 449,
      "us_trend_new_death": 4,
      "us_trend_maxdate": "2021-11-29"
    },
    {
      "abbr": "SD",
      "tot_cases": 164867,
      "tot_cases_last_24_hours": 0,
      "conf_cases": 0,
      "prob_cases": 0,
      "new_cases07": 2077,
      "new_deaths07": 19,
      "Seven_day_avg_new_cases_per_100k": 33.5,
      "Seven_day_avg_new_deaths_per_100k": 0.3,
      "Seven_day_cum_new_cases_per_100k": 234.8,
      "Seven_day_cum_new_deaths_per_100k": 2.2,
      "tot_death": 2328,
      "tot_death_last_24_hours": 0,
      "conf_death": 1950,
      "prob_death": 378,
      "death_100k": 263,
      "incidence": 18636,
      "id": 46,
      "fips": "46",
      "name": "South Dakota",
      "state_level_community_transmission": "high",
      "us_trend_new_case": 575,
      "us_trend_new_death": 8,
      "us_trend_maxdate": "2021-11-29"
    },
    {
      "abbr": "TN",
      "tot_cases": 1314188,
      "tot_cases_last_24_hours": 0,
      "conf_cases": 1027586,
      "prob_cases": 286602,
      "new_cases07": 7494,
      "new_deaths07": 140,
      "Seven_day_avg_new_cases_per_100k": 15.7,
      "Seven_day_avg_new_deaths_per_100k": 0.3,
      "Seven_day_cum_new_cases_per_100k": 109.7,
      "Seven_day_cum_new_deaths_per_100k": 2.1,
      "tot_death": 17001,
      "tot_death_last_24_hours": 0,
      "conf_death": 13505,
      "prob_death": 3496,
      "death_100k": 248,
      "incidence": 19244,
      "id": 47,
      "fips": "47",
      "name": "Tennessee",
      "state_level_community_transmission": "high",
      "us_trend_new_case": 718,
      "us_trend_new_death": 17,
      "us_trend_maxdate": "2021-11-29"
    },
    {
      "abbr": "TX",
      "tot_cases": 4309721,
      "tot_cases_last_24_hours": 0,
      "conf_cases": 0,
      "prob_cases": 0,
      "new_cases07": 16555,
      "new_deaths07": 321,
      "Seven_day_avg_new_cases_per_100k": 8.2,
      "Seven_day_avg_new_deaths_per_100k": 0.2,
      "Seven_day_cum_new_cases_per_100k": 57.1,
      "Seven_day_cum_new_deaths_per_100k": 1.1,
      "tot_death": 72529,
      "tot_death_last_24_hours": 0,
      "conf_death": null,
      "prob_death": null,
      "death_100k": 250,
      "incidence": 14863,
      "id": 48,
      "fips": "48",
      "name": "Texas",
      "state_level_community_transmission": "substantial",
      "us_trend_new_case": 2951,
      "us_trend_new_death": 148,
      "us_trend_maxdate": "2021-11-29"
    },
    {
      "abbr": "UT",
      "tot_cases": 594606,
      "tot_cases_last_24_hours": 0,
      "conf_cases": 594606,
      "prob_cases": 0,
      "new_cases07": 7848,
      "new_deaths07": 66,
      "Seven_day_avg_new_cases_per_100k": 35,
      "Seven_day_avg_new_deaths_per_100k": 0.3,
      "Seven_day_cum_new_cases_per_100k": 244.8,
      "Seven_day_cum_new_deaths_per_100k": 2.1,
      "tot_death": 3508,
      "tot_death_last_24_hours": 0,
      "conf_death": 3380,
      "prob_death": 128,
      "death_100k": 109,
      "incidence": 18547,
      "id": 49,
      "fips": "49",
      "name": "Utah",
      "state_level_community_transmission": "high",
      "us_trend_new_case": 2476,
      "us_trend_new_death": 21,
      "us_trend_maxdate": "2021-11-29"
    },
    {
      "abbr": "VA",
      "tot_cases": 969116,
      "tot_cases_last_24_hours": 0,
      "conf_cases": 714933,
      "prob_cases": 254183,
      "new_cases07": 9960,
      "new_deaths07": 137,
      "Seven_day_avg_new_cases_per_100k": 16.7,
      "Seven_day_avg_new_deaths_per_100k": 0.2,
      "Seven_day_cum_new_cases_per_100k": 116.7,
      "Seven_day_cum_new_deaths_per_100k": 1.6,
      "tot_death": 14710,
      "tot_death_last_24_hours": 0,
      "conf_death": 12350,
      "prob_death": 2360,
      "death_100k": 172,
      "incidence": 11354,
      "id": 51,
      "fips": "51",
      "name": "Virginia",
      "state_level_community_transmission": "high",
      "us_trend_new_case": 4229,
      "us_trend_new_death": 54,
      "us_trend_maxdate": "2021-11-29"
    },
    {
      "abbr": "VI",
      "tot_cases": 7511,
      "tot_cases_last_24_hours": 0,
      "conf_cases": 0,
      "prob_cases": 0,
      "new_cases07": 45,
      "new_deaths07": 1,
      "Seven_day_avg_new_cases_per_100k": 6.1,
      "Seven_day_avg_new_deaths_per_100k": 0.1,
      "Seven_day_cum_new_cases_per_100k": 42.3,
      "Seven_day_cum_new_deaths_per_100k": 0.9,
      "tot_death": 86,
      "tot_death_last_24_hours": 0,
      "conf_death": null,
      "prob_death": null,
      "death_100k": 80,
      "incidence": 7066,
      "id": 78,
      "fips": "78",
      "name": "Virgin Islands",
      "state_level_community_transmission": "moderate",
      "us_trend_new_case": 21,
      "us_trend_new_death": 1,
      "us_trend_maxdate": "2021-11-29"
    },
    {
      "abbr": "VT",
      "tot_cases": 46114,
      "tot_cases_last_24_hours": 0,
      "conf_cases": 0,
      "prob_cases": 0,
      "new_cases07": 3090,
      "new_deaths07": 9,
      "Seven_day_avg_new_cases_per_100k": 70.7,
      "Seven_day_avg_new_deaths_per_100k": 0.2,
      "Seven_day_cum_new_cases_per_100k": 495.2,
      "Seven_day_cum_new_deaths_per_100k": 1.4,
      "tot_death": 392,
      "tot_death_last_24_hours": 0,
      "conf_death": null,
      "prob_death": null,
      "death_100k": 62,
      "incidence": 7390,
      "id": 50,
      "fips": "50",
      "name": "Vermont",
      "state_level_community_transmission": "high",
      "us_trend_new_case": 1824,
      "us_trend_new_death": 4,
      "us_trend_maxdate": "2021-11-29"
    },
    {
      "abbr": "WA",
      "tot_cases": 773069,
      "tot_cases_last_24_hours": 0,
      "conf_cases": 0,
      "prob_cases": 0,
      "new_cases07": 7061,
      "new_deaths07": 118,
      "Seven_day_avg_new_cases_per_100k": 13.3,
      "Seven_day_avg_new_deaths_per_100k": 0.2,
      "Seven_day_cum_new_cases_per_100k": 92.7,
      "Seven_day_cum_new_deaths_per_100k": 1.6,
      "tot_death": 9257,
      "tot_death_last_24_hours": 0,
      "conf_death": null,
      "prob_death": null,
      "death_100k": 121,
      "incidence": 10152,
      "id": 53,
      "fips": "53",
      "name": "Washington",
      "state_level_community_transmission": "substantial",
      "us_trend_new_case": 986,
      "us_trend_new_death": 49,
      "us_trend_maxdate": "2021-11-29"
    },
    {
      "abbr": "WI",
      "tot_cases": 974871,
      "tot_cases_last_24_hours": 0,
      "conf_cases": 870249,
      "prob_cases": 104622,
      "new_cases07": 21449,
      "new_deaths07": 124,
      "Seven_day_avg_new_cases_per_100k": 52.6,
      "Seven_day_avg_new_deaths_per_100k": 0.3,
      "Seven_day_cum_new_cases_per_100k": 368.4,
      "Seven_day_cum_new_deaths_per_100k": 2.1,
      "tot_death": 9955,
      "tot_death_last_24_hours": 0,
      "conf_death": 8973,
      "prob_death": 982,
      "death_100k": 170,
      "incidence": 16743,
      "id": 55,
      "fips": "55",
      "name": "Wisconsin",
      "state_level_community_transmission": "high",
      "us_trend_new_case": 6580,
      "us_trend_new_death": 11,
      "us_trend_maxdate": "2021-11-29"
    },
    {
      "abbr": "WV",
      "tot_cases": 294014,
      "tot_cases_last_24_hours": 0,
      "conf_cases": 228658,
      "prob_cases": 65356,
      "new_cases07": 4490,
      "new_deaths07": 80,
      "Seven_day_avg_new_cases_per_100k": 35.8,
      "Seven_day_avg_new_deaths_per_100k": 0.6,
      "Seven_day_cum_new_cases_per_100k": 250.5,
      "Seven_day_cum_new_deaths_per_100k": 4.5,
      "tot_death": 4837,
      "tot_death_last_24_hours": 0,
      "conf_death": null,
      "prob_death": null,
      "death_100k": 269,
      "incidence": 16406,
      "id": 54,
      "fips": "54",
      "name": "West Virginia",
      "state_level_community_transmission": "high",
      "us_trend_new_case": 625,
      "us_trend_new_death": 20,
      "us_trend_maxdate": "2021-11-29"
    },
    {
      "abbr": "WY",
      "tot_cases": 110824,
      "tot_cases_last_24_hours": 0,
      "conf_cases": 87880,
      "prob_cases": 22944,
      "new_cases07": 1022,
      "new_deaths07": 0,
      "Seven_day_avg_new_cases_per_100k": 25.2,
      "Seven_day_avg_new_deaths_per_100k": 0,
      "Seven_day_cum_new_cases_per_100k": 176.6,
      "Seven_day_cum_new_deaths_per_100k": 0,
      "tot_death": 1347,
      "tot_death_last_24_hours": 0,
      "conf_death": 1347,
      "prob_death": 0,
      "death_100k": 232,
      "incidence": 19149,
      "id": 56,
      "fips": "56",
      "name": "Wyoming",
      "state_level_community_transmission": "high",
      "us_trend_new_case": 560,
      "us_trend_new_death": 0,
      "us_trend_maxdate": "2021-11-29"
    },
    {
      "abbr": "USA",
      "tot_cases": 48377531,
      "tot_cases_last_24_hours": 119404,
      "conf_cases": 27009723,
      "prob_cases": 4516295,
      "new_cases07": 561249,
      "new_deaths07": 5631,
      "Seven_day_avg_new_cases_per_100k": 24.2,
      "Seven_day_avg_new_deaths_per_100k": 0.2,
      "Seven_day_cum_new_cases_per_100k": 169.1,
      "Seven_day_cum_new_deaths_per_100k": 1.7,
      "tot_death": 778489,
      "tot_death_last_24_hours": 1661,
      "conf_death": 376172,
      "prob_death": 49023,
      "death_100k": 234,
      "incidence": 14572,
      "id": 0,
      "fips": "00",
      "name": "United States of America",
      "state_level_community_transmission": "high",
      "us_trend_new_case": 119404,
      "us_trend_new_death": 1661,
      "us_trend_maxdate": "2021-11-29"
    },
    {
      "abbr": "NY (including NYC)",
      "name": "NY (including NYC)",
      "Seven_day_cum_new_cases_per_100k": 224.8,
      "percent_positive_test_results_last_7_days": 4.8,
      "state_level_community_transmission": "high"
    }
  ]
}
